{"requestParameters":{"date":"2018/04/02","walkSpeed":"1.33","walkReluctance":"2.0","fromPlace":"48.448027,-71.07448399","maxWalkDistance":"3000","waitReluctance":"1.0","carSpeed":"33","numItineraries":"3","waitAtBeginningFactor":"0.4","mode":"TRANSIT,WALK","ignoreRealtimeUpdates":"false","stairsReluctance":"2.0","toPlace":"48.407318,-71.059717","time":"17:0:00"},"plan":{"date":1522702800000,"from":{"name":"Origin","lon":-71.07448399,"lat":48.448027,"orig":"","vertexType":"NORMAL"},"to":{"name":"Destination","lon":-71.059717,"lat":48.407318,"orig":"","vertexType":"NORMAL"},"itineraries":[{"duration":2793,"startTime":1522704388000,"endTime":1522707181000,"walkTime":783,"transitTime":1708,"waitingTime":302,"walkDistance":1014.4055263122228,"walkLimitExceeded":false,"elevationLost":0.0,"elevationGained":0.0,"transfers":1,"legs":[{"startTime":1522704388000,"endTime":1522704750000,"departureDelay":0,"arrivalDelay":0,"realTime":false,"distance":474.88599999999997,"pathway":false,"mode":"WALK","route":"","agencyTimeZoneOffset":-14400000,"interlineWithPreviousLeg":false,"from":{"name":"Origin","lon":-71.07448399,"lat":48.448027,"departure":1522704388000,"orig":"","vertexType":"NORMAL"},"to":{"name":"Boischatel / Cabot","stopId":"1:763","stopCode":"763","lon":-71.070142,"lat":48.449792,"arrival":1522704750000,"departure":1522704751000,"zoneId":"NA","stopIndex":27,"stopSequence":28,"vertexType":"TRANSIT"},"legGeometry":{"points":"ulufHvuxpLEk@Ks@I][gBMs@Ig@Cu@Co@AkA?k@y@Ja@B_@Ce@Q]Ua@g@GIQ]GWCQAq@@e@@e@@Iq@GYICA","length":28},"rentedBike":false,"transitLeg":false,"duration":362.0,"steps":[{"distance":208.91400000000002,"relativeDirection":"DEPART","streetName":"Rue de l'Aréna","absoluteDirection":"EAST","stayOn":false,"area":false,"bogusName":false,"lon":-71.07435584056401,"lat":48.447636667474086,"elevation":[]},{"distance":221.346,"relativeDirection":"LEFT","streetName":"Rue Cabot","absoluteDirection":"NORTH","stayOn":false,"area":false,"bogusName":false,"lon":-71.0716385,"lat":48.448087900000004,"elevation":[]},{"distance":44.626,"relativeDirection":"LEFT","streetName":"Rue de Boischatel","absoluteDirection":"NORTH","stayOn":false,"area":false,"bogusName":false,"lon":-71.0702047,"lat":48.449388000000006,"elevation":[]}]},{"startTime":1522704751000,"endTime":1522705200000,"departureDelay":0,"arrivalDelay":0,"realTime":false,"distance":2905.737028886756,"pathway":false,"mode":"BUS","route":"22","agencyName":"Société de Transport du Saguenay","agencyUrl":"http://ville.saguenay.ca/fr/services-aux-citoyens/transport-sts","agencyTimeZoneOffset":-14400000,"routeColor":"C0C000","routeType":3,"routeId":"1:22","routeTextColor":"000000","interlineWithPreviousLeg":false,"tripBlockId":"3","headsign":"Terminus Chicoutimi","agencyId":"0","tripId":"1:217208","serviceDate":"20180402","from":{"name":"Boischatel / Cabot","stopId":"1:763","stopCode":"763","lon":-71.070142,"lat":48.449792,"arrival":1522704750000,"departure":1522704751000,"zoneId":"NA","stopIndex":27,"stopSequence":28,"vertexType":"TRANSIT"},"to":{"name":"Terminus Chicoutimi","stopId":"1:1289","stopCode":"1289","lon":-71.066163,"lat":48.428677,"arrival":1522705200000,"departure":1522705500000,"zoneId":"NA","stopIndex":35,"stopSequence":36,"vertexType":"TRANSIT"},"legGeometry":{"points":"czufHb{wpLLFbAVH_AXeC@IdB_Mh@_EJk@x@x@bA`A|BrBnDrCl@f@|BlBrAbAj@d@ZTXNd@@lA[ZxDN|Ad@fAz@tB~AzDZ|@Zv@x@vBP\\h@~@PVrCmFhHqN~@eBr@cAt@_Av@}@RQPMz@k@tAe@REZG^Af@@X@VF`@Jn@XbClAr@Xt\\`PrAb@pA^hBTjAFj@Pb@JPHLLJNJRFXDT?X?ZEVEVKTMNMHMFOB}DWSGOSYcAN}FFkAF}DJyDd@wPV_HjAN~ALIzBQb@e@@","length":89},"routeShortName":"22","routeLongName":"Vanier","rentedBike":false,"transitLeg":true,"duration":449.0,"steps":[]},{"startTime":1522705500000,"endTime":1522706759000,"departureDelay":0,"arrivalDelay":0,"realTime":false,"distance":5344.788688857265,"pathway":false,"mode":"BUS","route":"15","agencyName":"Société de Transport du Saguenay","agencyUrl":"http://ville.saguenay.ca/fr/services-aux-citoyens/transport-sts","agencyTimeZoneOffset":-14400000,"routeColor":"FF00FF","routeType":3,"routeId":"1:15","routeTextColor":"FFFFFF","interlineWithPreviousLeg":false,"tripBlockId":"31","headsign":"Talbot / Barrette","agencyId":"0","tripId":"1:218144","serviceDate":"20180402","from":{"name":"Terminus Chicoutimi","stopId":"1:1289","stopCode":"1289","lon":-71.066163,"lat":48.428677,"arrival":1522705200000,"departure":1522705500000,"zoneId":"NA","stopIndex":0,"stopSequence":1,"vertexType":"TRANSIT"},"to":{"name":"Saguenéens  / Bach","stopId":"1:575","stopCode":"575","lon":-71.061104,"lat":48.403689,"arrival":1522706759000,"departure":1522706760000,"zoneId":"NA","stopIndex":23,"stopSequence":24,"vertexType":"TRANSIT"},"legGeometry":{"points":"evqfHpbwpLPiCjKx@HiEZkS\\aSN_K^eIrBpBvIpIr@r@\\mBfAaA`@gBOkB_@uF|DyL|DpDQ|@|@z@bA`ATw@dD~Ch@fA@`E~AjGuH`Iy@bBi@dCbEdEjJlJ`HbHlJpJ|J~JdAfALzDNzDrAdBrEKvBEbCv@d@TvFlC|DlBpMlGrB`AM}@hAwEC{B]oBiBmBsH_@_K{H`EgIvCaGfEoItDsH~DeI","length":58},"routeShortName":"15","routeLongName":"Term. Chic / Costco","rentedBike":false,"transitLeg":true,"duration":1259.0,"steps":[]},{"startTime":1522706760000,"endTime":1522707181000,"departureDelay":0,"arrivalDelay":0,"realTime":false,"distance":539.409,"pathway":false,"mode":"WALK","route":"","agencyTimeZoneOffset":-14400000,"interlineWithPreviousLeg":false,"from":{"name":"Saguenéens  / Bach","stopId":"1:575","stopCode":"575","lon":-71.061104,"lat":48.403689,"arrival":1522706759000,"departure":1522706760000,"zoneId":"NA","stopIndex":23,"stopSequence":24,"vertexType":"TRANSIT"},"to":{"name":"Destination","lon":-71.059717,"lat":48.407318,"arrival":1522707181000,"orig":"","vertexType":"NORMAL"},"legGeometry":{"points":"wylfHfcvpLgAnC}EuEeE}Dw@q@uApDuBsB","length":7},"rentedBike":false,"transitLeg":false,"duration":421.0,"steps":[{"distance":66.956,"relativeDirection":"DEPART","streetName":"Rue des Saguenéens","absoluteDirection":"NORTHWEST","stayOn":false,"area":false,"bogusName":false,"lon":-71.0611521754673,"lat":48.403646208471976,"elevation":[]},{"distance":313.272,"relativeDirection":"RIGHT","streetName":"Rue Bach","absoluteDirection":"NORTHEAST","stayOn":false,"area":false,"bogusName":false,"lon":-71.06187870000001,"lat":48.404006700000004,"elevation":[]},{"distance":80.757,"relativeDirection":"LEFT","streetName":"Rue Goulet","absoluteDirection":"NORTHWEST","stayOn":false,"area":false,"bogusName":false,"lon":-71.0596087,"lat":48.4063869,"elevation":[]},{"distance":78.424,"relativeDirection":"RIGHT","streetName":"Rue Ravel","absoluteDirection":"NORTHEAST","stayOn":false,"area":false,"bogusName":false,"lon":-71.0604952,"lat":48.4068125,"elevation":[]}]}],"tooSloped":false},{"duration":3020,"startTime":1522704179000,"endTime":1522707199000,"walkTime":318,"transitTime":2100,"waitingTime":602,"walkDistance":403.4010075154732,"walkLimitExceeded":false,"elevationLost":0.0,"elevationGained":0.0,"transfers":1,"legs":[{"startTime":1522704180000,"endTime":1522704900000,"departureDelay":0,"arrivalDelay":0,"realTime":false,"distance":4966.255246808459,"pathway":false,"mode":"BUS","route":"23","agencyName":"Société de Transport du Saguenay","agencyUrl":"http://ville.saguenay.ca/fr/services-aux-citoyens/transport-sts","agencyTimeZoneOffset":-14400000,"routeColor":"FF00FF","routeType":3,"routeId":"1:23","routeTextColor":"FFFFFF","interlineWithPreviousLeg":false,"tripBlockId":"4","headsign":"Terminus Chicoutimi","agencyId":"0","tripId":"1:217244","serviceDate":"20180402","from":{"name":"Aréna du Plateau","stopId":"1:784","stopCode":"784","lon":-71.074321,"lat":48.447524,"departure":1522704180000,"orig":"","zoneId":"NA","stopIndex":6,"stopSequence":7,"vertexType":"TRANSIT"},"to":{"name":"Terminus Chicoutimi","stopId":"1:1289","stopCode":"1289","lon":-71.066163,"lat":48.428677,"arrival":1522704900000,"departure":1522705500000,"zoneId":"NA","stopIndex":26,"stopSequence":27,"vertexType":"TRANSIT"},"legGeometry":{"points":"qlufHvuxpLGi@Is@Ou@Qw@Mo@Kw@ImAGoBAk@aALa@?YEUKc@Yc@_@KOIUGUEWAW?YBqAH_AXeC@IdB_Mh@_EJk@d@kDhAqI`AgHz@oGBU?UAWCWUwAWD]B]AUEoAc@kE}AOIq@g@g@u@]w@b@s@T[~CkFf@s@\\e@x@}@jAeAXQZStBaAh@]`@]`@i@l@kDF_@R{AFWFMPIPC`@BT@V?TAVKLENCLCJ@J@xAb@x@Zz@\\CP?R@N@NFLFF`GtBx@Xw@pG@l@B\\DXL\\RZDFXPf@N@v@Bp@Dr@l@~HNlAH\\@HLd@\\z@Xd@X\\RTXRr@Zn@PfExAvDpALnBJt@Pp@|@`DHZPn@`@rBNnAFr@DbA?bB@jABzA?p@A???A???A?A???A@??A?A@??A@?@A??@A@???@A@?@?@A@?@?@?@?@???@?@?@?@?@?@@@?@?@@@?@@@?@@@?@@?@@??@@@?E`@Kr@]rACVEl@I|AAr@JbAWJe@FUAM?a@Ke@YYWWa@v@}@RQPMz@k@tAe@REZG^Af@@X@VF`@Jn@XbClAr@Xt\\`PrAb@pA^hBTjAFj@Pb@JPHLLJNJRFXDT?X?ZEVEVKTMNMHMFOB}DWSGOSYcAN}FFkAF}DJyDd@wPV_HjAN~ALI`C","length":243},"routeShortName":"23","routeLongName":"Côte Verdun via Aréna du Plateau","rentedBike":false,"transitLeg":true,"duration":720.0,"steps":[]},{"startTime":1522705500000,"endTime":1522706880000,"departureDelay":0,"arrivalDelay":0,"realTime":false,"distance":8921.890108417734,"pathway":false,"mode":"BUS","route":"12","agencyName":"Société de Transport du Saguenay","agencyUrl":"http://ville.saguenay.ca/fr/services-aux-citoyens/transport-sts","agencyTimeZoneOffset":-14400000,"routeColor":"556B2F","routeType":3,"routeId":"1:12","routeTextColor":"FFFFFF","interlineWithPreviousLeg":false,"tripBlockId":"27","headsign":"Terminus UQAC","agencyId":"0","tripId":"1:218022","serviceDate":"20180402","from":{"name":"Terminus Chicoutimi","stopId":"1:1289","stopCode":"1289","lon":-71.066163,"lat":48.428677,"arrival":1522704900000,"departure":1522705500000,"zoneId":"NA","stopIndex":0,"stopSequence":1,"vertexType":"TRANSIT"},"to":{"name":"Champs-Élysées / Chopin","stopId":"1:584","stopCode":"584","lon":-71.058412,"lat":48.409805,"arrival":1522706880000,"departure":1522706881000,"zoneId":"NA","stopIndex":29,"stopSequence":30,"vertexType":"TRANSIT"},"legGeometry":{"points":"evqfHpbwpLpFcj@IaKmFy^_DaZz@u]SeV}@aNs@gKToKd@gTnCyHkGuLqFqJ_DeFf@iIvGsKlIrH`JlH`EfDnOdIdGlGjL|BzBiLv@}L`b@fNvVvrCdRvMcAjKcP~b@","length":30},"routeShortName":"12","routeLongName":"Rivière du Moulin","rentedBike":false,"transitLeg":true,"duration":1380.0,"steps":[]},{"startTime":1522706881000,"endTime":1522707199000,"departureDelay":0,"arrivalDelay":0,"realTime":false,"distance":403.298,"pathway":false,"mode":"WALK","route":"","agencyTimeZoneOffset":-14400000,"interlineWithPreviousLeg":false,"from":{"name":"Champs-Élysées / Chopin","stopId":"1:584","stopCode":"584","lon":-71.058412,"lat":48.409805,"arrival":1522706880000,"departure":1522706881000,"zoneId":"NA","stopIndex":29,"stopSequence":30,"vertexType":"TRANSIT"},"to":{"name":"Destination","lon":-71.059717,"lat":48.407318,"arrival":1522707199000,"orig":"","vertexType":"NORMAL"},"legGeometry":{"points":"{_nfHprupL?@o@|A|@h@hAd@rAsDfH`H","length":7},"rentedBike":false,"transitLeg":false,"duration":318.0,"steps":[{"distance":44.609,"relativeDirection":"DEPART","streetName":"Rue des Champs-Élysées","absoluteDirection":"NORTHWEST","stayOn":false,"area":false,"bogusName":false,"lon":-71.05848639303342,"lat":48.40974208921815,"elevation":[]},{"distance":81.742,"relativeDirection":"LEFT","streetName":"Rue Bizet","absoluteDirection":"SOUTHWEST","stayOn":false,"area":false,"bogusName":false,"lon":-71.0589618,"lat":48.409989800000005,"elevation":[]},{"distance":80.733,"relativeDirection":"LEFT","streetName":"Rue Plamondon","absoluteDirection":"SOUTHEAST","stayOn":false,"area":false,"bogusName":false,"lon":-71.0593601,"lat":48.4093053,"elevation":[]},{"distance":196.214,"relativeDirection":"RIGHT","streetName":"Rue Ravel","absoluteDirection":"SOUTHWEST","stayOn":false,"area":false,"bogusName":false,"lon":-71.0584692,"lat":48.4088841,"elevation":[]}]}],"tooSloped":false},{"duration":3020,"startTime":1522705979000,"endTime":1522708999000,"walkTime":318,"transitTime":2100,"waitingTime":602,"walkDistance":403.4010075154732,"walkLimitExceeded":false,"elevationLost":0.0,"elevationGained":0.0,"transfers":1,"legs":[{"startTime":1522705980000,"endTime":1522706700000,"departureDelay":0,"arrivalDelay":0,"realTime":false,"distance":4966.255246808459,"pathway":false,"mode":"BUS","route":"23","agencyName":"Société de Transport du Saguenay","agencyUrl":"http://ville.saguenay.ca/fr/services-aux-citoyens/transport-sts","agencyTimeZoneOffset":-14400000,"routeColor":"FF00FF","routeType":3,"routeId":"1:23","routeTextColor":"FFFFFF","interlineWithPreviousLeg":false,"tripBlockId":"5","headsign":"Terminus Chicoutimi","agencyId":"0","tripId":"1:217272","serviceDate":"20180402","from":{"name":"Aréna du Plateau","stopId":"1:784","stopCode":"784","lon":-71.074321,"lat":48.447524,"departure":1522705980000,"orig":"","zoneId":"NA","stopIndex":6,"stopSequence":7,"vertexType":"TRANSIT"},"to":{"name":"Terminus Chicoutimi","stopId":"1:1289","stopCode":"1289","lon":-71.066163,"lat":48.428677,"arrival":1522706700000,"departure":1522707300000,"zoneId":"NA","stopIndex":26,"stopSequence":27,"vertexType":"TRANSIT"},"legGeometry":{"points":"qlufHvuxpLGi@Is@Ou@Qw@Mo@Kw@ImAGoBAk@aALa@?YEUKc@Yc@_@KOIUGUEWAW?YBqAH_AXeC@IdB_Mh@_EJk@d@kDhAqI`AgHz@oGBU?UAWCWUwAWD]B]AUEoAc@kE}AOIq@g@g@u@]w@b@s@T[~CkFf@s@\\e@x@}@jAeAXQZStBaAh@]`@]`@i@l@kDF_@R{AFWFMPIPC`@BT@V?TAVKLENCLCJ@J@xAb@x@Zz@\\CP?R@N@NFLFF`GtBx@Xw@pG@l@B\\DXL\\RZDFXPf@N@v@Bp@Dr@l@~HNlAH\\@HLd@\\z@Xd@X\\RTXRr@Zn@PfExAvDpALnBJt@Pp@|@`DHZPn@`@rBNnAFr@DbA?bB@jABzA?p@A???A???A?A???A@??A?A@??A@?@A??@A@???@A@?@?@A@?@?@?@?@???@?@?@?@?@?@@@?@?@@@?@@@?@@@?@@?@@??@@@?E`@Kr@]rACVEl@I|AAr@JbAWJe@FUAM?a@Ke@YYWWa@v@}@RQPMz@k@tAe@REZG^Af@@X@VF`@Jn@XbClAr@Xt\\`PrAb@pA^hBTjAFj@Pb@JPHLLJNJRFXDT?X?ZEVEVKTMNMHMFOB}DWSGOSYcAN}FFkAF}DJyDd@wPV_HjAN~ALI`C","length":243},"routeShortName":"23","routeLongName":"Côte Verdun via Aréna du Plateau","rentedBike":false,"transitLeg":true,"duration":720.0,"steps":[]},{"startTime":1522707300000,"endTime":1522708680000,"departureDelay":0,"arrivalDelay":0,"realTime":false,"distance":8921.890108417734,"pathway":false,"mode":"BUS","route":"12","agencyName":"Société de Transport du Saguenay","agencyUrl":"http://ville.saguenay.ca/fr/services-aux-citoyens/transport-sts","agencyTimeZoneOffset":-14400000,"routeColor":"556B2F","routeType":3,"routeId":"1:12","routeTextColor":"FFFFFF","interlineWithPreviousLeg":false,"tripBlockId":"28","headsign":"Terminus UQAC","agencyId":"0","tripId":"1:218049","serviceDate":"20180402","from":{"name":"Terminus Chicoutimi","stopId":"1:1289","stopCode":"1289","lon":-71.066163,"lat":48.428677,"arrival":1522706700000,"departure":1522707300000,"zoneId":"NA","stopIndex":0,"stopSequence":1,"vertexType":"TRANSIT"},"to":{"name":"Champs-Élysées / Chopin","stopId":"1:584","stopCode":"584","lon":-71.058412,"lat":48.409805,"arrival":1522708680000,"departure":1522708681000,"zoneId":"NA","stopIndex":29,"stopSequence":30,"vertexType":"TRANSIT"},"legGeometry":{"points":"evqfHpbwpLpFcj@IaKmFy^_DaZz@u]SeV}@aNs@gKToKd@gTnCyHkGuLqFqJ_DeFf@iIvGsKlIrH`JlH`EfDnOdIdGlGjL|BzBiLv@}L`b@fNvVvrCdRvMcAjKcP~b@","length":30},"routeShortName":"12","routeLongName":"Rivière du Moulin","rentedBike":false,"transitLeg":true,"duration":1380.0,"steps":[]},{"startTime":1522708681000,"endTime":1522708999000,"departureDelay":0,"arrivalDelay":0,"realTime":false,"distance":403.298,"pathway":false,"mode":"WALK","route":"","agencyTimeZoneOffset":-14400000,"interlineWithPreviousLeg":false,"from":{"name":"Champs-Élysées / Chopin","stopId":"1:584","stopCode":"584","lon":-71.058412,"lat":48.409805,"arrival":1522708680000,"departure":1522708681000,"zoneId":"NA","stopIndex":29,"stopSequence":30,"vertexType":"TRANSIT"},"to":{"name":"Destination","lon":-71.059717,"lat":48.407318,"arrival":1522708999000,"orig":"","vertexType":"NORMAL"},"legGeometry":{"points":"{_nfHprupL?@o@|A|@h@hAd@rAsDfH`H","length":7},"rentedBike":false,"transitLeg":false,"duration":318.0,"steps":[{"distance":44.609,"relativeDirection":"DEPART","streetName":"Rue des Champs-Élysées","absoluteDirection":"NORTHWEST","stayOn":false,"area":false,"bogusName":false,"lon":-71.05848639303342,"lat":48.40974208921815,"elevation":[]},{"distance":81.742,"relativeDirection":"LEFT","streetName":"Rue Bizet","absoluteDirection":"SOUTHWEST","stayOn":false,"area":false,"bogusName":false,"lon":-71.0589618,"lat":48.409989800000005,"elevation":[]},{"distance":80.733,"relativeDirection":"LEFT","streetName":"Rue Plamondon","absoluteDirection":"SOUTHEAST","stayOn":false,"area":false,"bogusName":false,"lon":-71.0593601,"lat":48.4093053,"elevation":[]},{"distance":196.214,"relativeDirection":"RIGHT","streetName":"Rue Ravel","absoluteDirection":"SOUTHWEST","stayOn":false,"area":false,"bogusName":false,"lon":-71.0584692,"lat":48.4088841,"elevation":[]}]}],"tooSloped":false}]},"debugOutput":{"precalculationTime":26,"pathCalculationTime":26,"pathTimes":[14,6,6],"renderingTime":0,"totalTime":52,"timedOut":false},"elevationMetadata":{"ellipsoidToGeoidDifference":-28.885904201182168,"geoidElevation":false}}