{"requestParameters":{"date":"2018/04/02","walkSpeed":"1.33","walkReluctance":"2.0","fromPlace":"48.394995,-71.076396","maxWalkDistance":"3000","waitReluctance":"1.0","carSpeed":"33","numItineraries":"3","waitAtBeginningFactor":"0.4","mode":"TRANSIT,WALK","ignoreRealtimeUpdates":"false","stairsReluctance":"2.0","toPlace":"48.423269,-71.05968099","time":"8:15:00"},"plan":{"date":1522671300000,"from":{"name":"Origin","lon":-71.076396,"lat":48.394995,"orig":"","vertexType":"NORMAL"},"to":{"name":"Destination","lon":-71.05968099,"lat":48.423269,"orig":"","vertexType":"NORMAL"},"itineraries":[{"duration":1745,"startTime":1522671980000,"endTime":1522673725000,"walkTime":1012,"transitTime":731,"waitingTime":2,"walkDistance":1299.7381804439588,"walkLimitExceeded":false,"elevationLost":0.0,"elevationGained":0.0,"transfers":0,"legs":[{"startTime":1522671980000,"endTime":1522672559000,"departureDelay":0,"arrivalDelay":0,"realTime":false,"distance":747.35,"pathway":false,"mode":"WALK","route":"","agencyTimeZoneOffset":-14400000,"interlineWithPreviousLeg":false,"from":{"name":"Origin","lon":-71.076396,"lat":48.394995,"departure":1522671980000,"orig":"","vertexType":"NORMAL"},"to":{"name":"boul. Talbot / boul. Barrette","stopId":"1:49","stopCode":"49","lon":-71.069502,"lat":48.394497,"arrival":1522672559000,"departure":1522672560000,"zoneId":"NA","stopIndex":7,"stopSequence":8,"vertexType":"TRANSIT"},"legGeometry":{"points":"mbkfH|bypLR_Ca@Ie@GyA[]ViA_Ah@wBr@sCVaA`H{Q@GFMPc@OO}BmC","length":16},"rentedBike":false,"transitLeg":false,"duration":579.0,"steps":[{"distance":49.204,"relativeDirection":"DEPART","streetName":"Rue Flaubert","absoluteDirection":"EAST","stayOn":false,"area":false,"bogusName":false,"lon":-71.0764685121978,"lat":48.39479671419616,"elevation":[]},{"distance":158.336,"relativeDirection":"LEFT","streetName":"Rue Jacques-Ferron","absoluteDirection":"NORTH","stayOn":false,"area":false,"bogusName":false,"lon":-71.07582090000001,"lat":48.3946923,"elevation":[]},{"distance":441.378,"relativeDirection":"RIGHT","streetName":"Boulevard Barrette","absoluteDirection":"SOUTHEAST","stayOn":false,"area":false,"bogusName":false,"lon":-71.0753974,"lat":48.396028400000006,"elevation":[]},{"distance":98.432,"relativeDirection":"LEFT","streetName":"Boulevard Talbot","absoluteDirection":"NORTHEAST","stayOn":false,"area":false,"bogusName":false,"lon":-71.07041720000001,"lat":48.393846,"elevation":[]}]},{"startTime":1522672560000,"endTime":1522673291000,"departureDelay":0,"arrivalDelay":0,"realTime":false,"distance":3947.533247969134,"pathway":false,"mode":"BUS","route":"175","agencyName":"Société de Transport du Saguenay","agencyUrl":"http://ville.saguenay.ca/fr/services-aux-citoyens/transport-sts","agencyTimeZoneOffset":-14400000,"routeColor":"FF00FF","routeType":3,"routeId":"1:175","routeTextColor":"FFFFFF","interlineWithPreviousLeg":false,"tripBlockId":"79","headsign":"Terminus Chicoutimi","agencyId":"0","tripId":"1:218650","serviceDate":"20180402","from":{"name":"boul. Talbot / boul. Barrette","stopId":"1:49","stopCode":"49","lon":-71.069502,"lat":48.394497,"arrival":1522672559000,"departure":1522672560000,"zoneId":"NA","stopIndex":7,"stopSequence":8,"vertexType":"TRANSIT"},"to":{"name":"Cégep de Chicoutimi (Bégin)","stopId":"1:66","stopCode":"66","lon":-71.056314,"lat":48.424377,"arrival":1522673291000,"departure":1522673292000,"zoneId":"NA","stopIndex":17,"stopSequence":18,"vertexType":"TRANSIT"},"legGeometry":{"points":"aakfHlxwpLiAoAgEsFkFsHqJ_N}FkImPkOuO{N_U_TcNgNcBcB{E`Jc@x@qG~@{BlAk@XgSrQqB_GAeFiEeEOt@gAeA_A_ATm@yAwAgBeBqDnL@nBF`@f@|C[dCuAfB]xAs@OmCmC","length":35},"routeShortName":"175","routeLongName":"Term. Chic / Costco","rentedBike":false,"transitLeg":true,"duration":731.0,"steps":[]},{"startTime":1522673292000,"endTime":1522673725000,"departureDelay":0,"arrivalDelay":0,"realTime":false,"distance":552.166,"pathway":false,"mode":"WALK","route":"","agencyTimeZoneOffset":-14400000,"interlineWithPreviousLeg":false,"from":{"name":"Cégep de Chicoutimi (Bégin)","stopId":"1:66","stopCode":"66","lon":-71.056314,"lat":48.424377,"arrival":1522673291000,"departure":1522673292000,"zoneId":"NA","stopIndex":17,"stopSequence":18,"vertexType":"TRANSIT"},"to":{"name":"Destination","lon":-71.05968099,"lat":48.423269,"arrival":1522673725000,"orig":"","vertexType":"NORMAL"},"legGeometry":{"points":"k{pfH`eupL[[k@q@S@C~ACvCIvFClCBdAGzCnAFbDPJ?LiA","length":14},"rentedBike":false,"transitLeg":false,"duration":433.0,"steps":[{"distance":61.132,"relativeDirection":"DEPART","streetName":"sidewalk","absoluteDirection":"NORTHEAST","stayOn":false,"area":false,"bogusName":true,"lon":-71.0563254039123,"lat":48.42438196430904,"elevation":[]},{"distance":319.182,"relativeDirection":"LEFT","streetName":"Rue Price Est","absoluteDirection":"WEST","stayOn":false,"area":false,"bogusName":false,"lon":-71.0559435,"lat":48.424848700000005,"elevation":[]},{"distance":143.156,"relativeDirection":"LEFT","streetName":"Rue La Fontaine","absoluteDirection":"SOUTH","stayOn":false,"area":false,"bogusName":false,"lon":-71.06026100000001,"lat":48.424977000000005,"elevation":[]},{"distance":28.696,"relativeDirection":"LEFT","streetName":"path","absoluteDirection":"EAST","stayOn":false,"area":false,"bogusName":true,"lon":-71.06039840000001,"lat":48.423692800000005,"elevation":[]}]}],"tooSloped":false},{"duration":1867,"startTime":1522672466000,"endTime":1522674333000,"walkTime":758,"transitTime":1107,"waitingTime":2,"walkDistance":956.3087443529082,"walkLimitExceeded":false,"elevationLost":0.0,"elevationGained":0.0,"transfers":0,"legs":[{"startTime":1522672466000,"endTime":1522672824000,"departureDelay":0,"arrivalDelay":0,"realTime":false,"distance":453.167,"pathway":false,"mode":"WALK","route":"","agencyTimeZoneOffset":-14400000,"interlineWithPreviousLeg":false,"from":{"name":"Origin","lon":-71.076396,"lat":48.394995,"departure":1522672466000,"orig":"","vertexType":"NORMAL"},"to":{"name":"boul. Barrette / Jacques-Ferron","stopId":"1:271","stopCode":"271","lon":-71.07524,"lat":48.395917,"arrival":1522672824000,"departure":1522672825000,"zoneId":"NA","stopIndex":33,"stopSequence":34,"vertexType":"TRANSIT"},"legGeometry":{"points":"mbkfH|bypLR_Ca@Ie@GyA[]V_@jBaAdDeAi@f@kBlAyE","length":11},"rentedBike":false,"transitLeg":false,"duration":358.0,"steps":[{"distance":49.204,"relativeDirection":"DEPART","streetName":"Rue Flaubert","absoluteDirection":"EAST","stayOn":false,"area":false,"bogusName":false,"lon":-71.0764685121978,"lat":48.39479671419616,"elevation":[]},{"distance":225.4,"relativeDirection":"LEFT","streetName":"Rue Jacques-Ferron","absoluteDirection":"NORTH","stayOn":false,"area":false,"bogusName":false,"lon":-71.07582090000001,"lat":48.3946923,"elevation":[]},{"distance":41.863,"relativeDirection":"RIGHT","streetName":"path","absoluteDirection":"NORTH","stayOn":false,"area":false,"bogusName":true,"lon":-71.0770823,"lat":48.3961436,"elevation":[]},{"distance":136.7,"relativeDirection":"RIGHT","streetName":"bike path","absoluteDirection":"SOUTHEAST","stayOn":true,"area":false,"bogusName":true,"lon":-71.0768749,"lat":48.396494000000004,"elevation":[]}]},{"startTime":1522672825000,"endTime":1522672860000,"departureDelay":0,"arrivalDelay":0,"realTime":false,"distance":506.59896771254614,"pathway":false,"mode":"BUS","route":"14","agencyName":"Société de Transport du Saguenay","agencyUrl":"http://ville.saguenay.ca/fr/services-aux-citoyens/transport-sts","agencyTimeZoneOffset":-14400000,"routeColor":"C0C000","routeType":3,"routeId":"1:14","routeTextColor":"000000","interlineWithPreviousLeg":false,"tripBlockId":"32","headsign":"Talbot / Barrette","agencyId":"0","tripId":"1:218150","serviceDate":"20180402","from":{"name":"boul. Barrette / Jacques-Ferron","stopId":"1:271","stopCode":"271","lon":-71.07524,"lat":48.395917,"arrival":1522672824000,"departure":1522672825000,"zoneId":"NA","stopIndex":33,"stopSequence":34,"vertexType":"TRANSIT"},"to":{"name":"Roitelets / Sapins","stopId":"1:1543","stopCode":"1543","lon":-71.069553,"lat":48.393375,"arrival":1522672860000,"departure":1522672860000,"zoneId":"NA","stopIndex":35,"stopSequence":36,"vertexType":"TRANSIT"},"legGeometry":{"points":"{ikfH|zxpLrByHfAqCvH_SLa@","length":5},"routeShortName":"14","routeLongName":"Coopérative","rentedBike":false,"transitLeg":true,"duration":35.0,"steps":[]},{"startTime":1522672860000,"endTime":1522673932000,"departureDelay":0,"arrivalDelay":0,"realTime":false,"distance":6677.593015986816,"pathway":false,"mode":"BUS","route":"15","agencyName":"Société de Transport du Saguenay","agencyUrl":"http://ville.saguenay.ca/fr/services-aux-citoyens/transport-sts","agencyTimeZoneOffset":-14400000,"routeColor":"FF00FF","routeType":3,"routeId":"1:15","routeTextColor":"FFFFFF","interlineWithPreviousLeg":true,"tripBlockId":"32","headsign":"Terminus Chicoutimi","agencyId":"0","tripId":"1:218151","serviceDate":"20180402","from":{"name":"Roitelets / Sapins","stopId":"1:1543","stopCode":"1543","lon":-71.069553,"lat":48.393375,"arrival":1522672860000,"departure":1522672860000,"zoneId":"NA","stopIndex":0,"stopSequence":1,"vertexType":"TRANSIT"},"to":{"name":"Centre George Vézina (Bégin)","stopId":"1:583","stopCode":"583","lon":-71.0606,"lat":48.4201,"arrival":1522673932000,"departure":1522673933000,"zoneId":"NA","stopIndex":28,"stopSequence":29,"vertexType":"TRANSIT"},"legGeometry":{"points":"_zjfHfwwpLx@}BHa@NaADq@@y@Cy@I{@Ka@O[Sg@c@mAWwAMyA?EC]?wABuABmFB{@BmDFuH@i@F[FsC@c@TuGEGVsHPuDLuBXsFDoA?W@]Cu@GcAKu@Q_ASo@a@y@a@o@MOUUeCqBiDsDqE{EiAcAcB_AqBgA_AQaBSaBG_@Bu@FG?h@fNKnDpCfBkAzDgA}@y@q@sDy@GAeGT~@~KKrKyAnL[hBUxAm@nCcAlDeCvGmA|CUr@}@~A_@\\_DvCEZcA|@UP_@d@Yl@oBdFeCxG_CfGYVQXS\\dK|HlFZbC\\p@zA\\rB@hBiArG{BNw@FiG}@iDwAECcCcBo@y@sEeGe@o@qAa@m@MoB?C@}BZwAc@oA_Bs@gDCKZ{Di@QECc@_@sAkAoBwB_EcE{A_BoAmAk@o@cCaCkIkIaJaJ","length":127},"routeShortName":"15","routeLongName":"Term. Chic / Costco","rentedBike":false,"transitLeg":true,"duration":1072.0,"steps":[]},{"startTime":1522673933000,"endTime":1522674333000,"departureDelay":0,"arrivalDelay":0,"realTime":false,"distance":502.894,"pathway":false,"mode":"WALK","route":"","agencyTimeZoneOffset":-14400000,"interlineWithPreviousLeg":false,"from":{"name":"Centre George Vézina (Bégin)","stopId":"1:583","stopCode":"583","lon":-71.0606,"lat":48.4201,"arrival":1522673932000,"departure":1522673933000,"zoneId":"NA","stopIndex":28,"stopSequence":29,"vertexType":"TRANSIT"},"to":{"name":"Destination","lon":-71.05968099,"lat":48.423269,"arrival":1522674333000,"orig":"","vertexType":"NORMAL"},"legGeometry":{"points":"y`pfHf`vpLSScAeAg@i@KMYYStDcACeFe@k@Cu@E]Aq@Eq@ELiA","length":15},"rentedBike":false,"transitLeg":false,"duration":400.0,"steps":[{"distance":112.547,"relativeDirection":"DEPART","streetName":"Rue Bégin","absoluteDirection":"NORTHEAST","stayOn":false,"area":false,"bogusName":false,"lon":-71.06067782404135,"lat":48.420134620151806,"elevation":[]},{"distance":67.849,"relativeDirection":"LEFT","streetName":"Boulevard de l'Université","absoluteDirection":"WEST","stayOn":false,"area":false,"bogusName":false,"lon":-71.05981580000001,"lat":48.4209693,"elevation":[]},{"distance":293.80199999999996,"relativeDirection":"RIGHT","streetName":"Rue La Fontaine","absoluteDirection":"NORTH","stayOn":false,"area":false,"bogusName":false,"lon":-71.06072490000001,"lat":48.4210605,"elevation":[]},{"distance":28.696,"relativeDirection":"RIGHT","streetName":"path","absoluteDirection":"EAST","stayOn":false,"area":false,"bogusName":true,"lon":-71.06039840000001,"lat":48.423692800000005,"elevation":[]}]}],"tooSloped":false},{"duration":2033,"startTime":1522672647000,"endTime":1522674680000,"walkTime":693,"transitTime":1338,"waitingTime":2,"walkDistance":868.7999097659203,"walkLimitExceeded":false,"elevationLost":0.0,"elevationGained":0.0,"transfers":0,"legs":[{"startTime":1522672647000,"endTime":1522672968000,"departureDelay":0,"arrivalDelay":0,"realTime":false,"distance":397.586,"pathway":false,"mode":"WALK","route":"","agencyTimeZoneOffset":-14400000,"interlineWithPreviousLeg":false,"from":{"name":"Origin","lon":-71.076396,"lat":48.394995,"departure":1522672647000,"orig":"","vertexType":"NORMAL"},"to":{"name":"boul. Barrette / Cent Associés","stopId":"1:1596","stopCode":"1596","lon":-71.07741,"lat":48.396946,"arrival":1522672968000,"departure":1522672969000,"zoneId":"NA","stopIndex":2,"stopSequence":3,"vertexType":"TRANSIT"},"legGeometry":{"points":"mbkfH|bypLR_Ca@Ie@GyA[]V_@jBaAdDeAi@GIWS[fAWdA","length":13},"rentedBike":false,"transitLeg":false,"duration":321.0,"steps":[{"distance":49.204,"relativeDirection":"DEPART","streetName":"Rue Flaubert","absoluteDirection":"EAST","stayOn":false,"area":false,"bogusName":false,"lon":-71.0764685121978,"lat":48.39479671419616,"elevation":[]},{"distance":225.4,"relativeDirection":"LEFT","streetName":"Rue Jacques-Ferron","absoluteDirection":"NORTH","stayOn":false,"area":false,"bogusName":false,"lon":-71.07582090000001,"lat":48.3946923,"elevation":[]},{"distance":62.658,"relativeDirection":"RIGHT","streetName":"path","absoluteDirection":"NORTH","stayOn":false,"area":false,"bogusName":true,"lon":-71.0770823,"lat":48.3961436,"elevation":[]},{"distance":60.324,"relativeDirection":"LEFT","streetName":"Boulevard Barrette","absoluteDirection":"NORTHWEST","stayOn":false,"area":false,"bogusName":false,"lon":-71.07672170000001,"lat":48.396650900000004,"elevation":[]}]},{"startTime":1522672969000,"endTime":1522674307000,"departureDelay":0,"arrivalDelay":0,"realTime":false,"distance":8155.674098840501,"pathway":false,"mode":"BUS","route":"14","agencyName":"Société de Transport du Saguenay","agencyUrl":"http://ville.saguenay.ca/fr/services-aux-citoyens/transport-sts","agencyTimeZoneOffset":-14400000,"routeColor":"C0C000","routeType":3,"routeId":"1:14","routeTextColor":"000000","interlineWithPreviousLeg":false,"tripBlockId":"33","headsign":"Terminus Chicoutimi","agencyId":"0","tripId":"1:218176","serviceDate":"20180402","from":{"name":"boul. Barrette / Cent Associés","stopId":"1:1596","stopCode":"1596","lon":-71.07741,"lat":48.396946,"arrival":1522672968000,"departure":1522672969000,"zoneId":"NA","stopIndex":2,"stopSequence":3,"vertexType":"TRANSIT"},"to":{"name":"Jacques-Cartier / Labrecque (Manoir Champlain)","stopId":"1:68","stopCode":"68","lon":-71.05805,"lat":48.426307,"arrival":1522674307000,"departure":1522674308000,"zoneId":"NA","stopIndex":34,"stopSequence":35,"vertexType":"TRANSIT"},"legGeometry":{"points":"uokfH~hypLcD`Mi@dCgChLmCzMwGd\\aDxOdFtFhCtCdDY|F_On@aB`B_GNoBvAyT|@sNuAyAuF}F}AaB_BkAC@qC\\gAWiBwBiKgMiCwEgEyHCGy@uB}@rAa@nAc@lFEf@mGvUYfAqCs@ICMCqFmDc@s@mAkBuEoESUgAhDiAfD}@zDyAcA_@Um@U{AWgB_Au@s@EEsBkCqFgF{IiI][aBhE}@}@oBmBwE{EwE{Ej@mBZeAa@SyEQg@CPcALuCx@{b@t@{[XoDd@sBl@iB~@gA`G{F{A{D_@sBFqDOq@iG{FGIoCkCgBgBsDpLHzBBT`@~COnBQf@gAjAg@bBuDmDmFgFa@_@w@s@CfAOrBEtAGbA?jBQtC?|@","length":103},"routeShortName":"14","routeLongName":"Coopérative","rentedBike":false,"transitLeg":true,"duration":1338.0,"steps":[]},{"startTime":1522674308000,"endTime":1522674680000,"departureDelay":0,"arrivalDelay":0,"realTime":false,"distance":470.95000000000005,"pathway":false,"mode":"WALK","route":"","agencyTimeZoneOffset":-14400000,"interlineWithPreviousLeg":false,"from":{"name":"Jacques-Cartier / Labrecque (Manoir Champlain)","stopId":"1:68","stopCode":"68","lon":-71.05805,"lat":48.426307,"arrival":1522674307000,"departure":1522674308000,"zoneId":"NA","stopIndex":34,"stopSequence":35,"vertexType":"TRANSIT"},"to":{"name":"Destination","lon":-71.05968099,"lat":48.423269,"arrival":1522674680000,"orig":"","vertexType":"NORMAL"},"legGeometry":{"points":"agqfHzoupL?VAT?`@CfBhG^BdAGzCnAFbDPJ?LiA","length":12},"rentedBike":false,"transitLeg":false,"duration":372.0,"steps":[{"distance":68.239,"relativeDirection":"DEPART","streetName":"Rue Jacques-Cartier Est","absoluteDirection":"WEST","stayOn":false,"area":false,"bogusName":false,"lon":-71.05805450282384,"lat":48.426254314622405,"elevation":[]},{"distance":147.775,"relativeDirection":"LEFT","streetName":"Rue Maltais","absoluteDirection":"SOUTH","stayOn":false,"area":false,"bogusName":false,"lon":-71.0589782,"lat":48.426284100000004,"elevation":[]},{"distance":83.084,"relativeDirection":"RIGHT","streetName":"Rue Price Est","absoluteDirection":"WEST","stayOn":false,"area":false,"bogusName":false,"lon":-71.0591387,"lat":48.424959400000006,"elevation":[]},{"distance":143.156,"relativeDirection":"LEFT","streetName":"Rue La Fontaine","absoluteDirection":"SOUTH","stayOn":false,"area":false,"bogusName":false,"lon":-71.06026100000001,"lat":48.424977000000005,"elevation":[]},{"distance":28.696,"relativeDirection":"LEFT","streetName":"path","absoluteDirection":"EAST","stayOn":false,"area":false,"bogusName":true,"lon":-71.06039840000001,"lat":48.423692800000005,"elevation":[]}]}],"tooSloped":false}]},"debugOutput":{"precalculationTime":35,"pathCalculationTime":26,"pathTimes":[15,5,6],"renderingTime":0,"totalTime":61,"timedOut":false},"elevationMetadata":{"ellipsoidToGeoidDifference":-28.885904201182168,"geoidElevation":false}}