{"requestParameters":{"date":"2018/04/02","walkSpeed":"1.33","walkReluctance":"2.0","fromPlace":"48.44911,-71.08157599","maxWalkDistance":"3000","waitReluctance":"1.0","carSpeed":"33","numItineraries":"3","waitAtBeginningFactor":"0.4","mode":"TRANSIT,WALK","ignoreRealtimeUpdates":"false","stairsReluctance":"2.0","toPlace":"48.447474,-71.059915","time":"16:0:00"},"plan":{"date":1522699200000,"from":{"name":"Origin","lon":-71.08157599,"lat":48.44911,"orig":"","vertexType":"NORMAL"},"to":{"name":"Destination","lon":-71.059915,"lat":48.447474,"orig":"","vertexType":"NORMAL"},"itineraries":[{"duration":1477,"startTime":1522699200000,"endTime":1522700677000,"walkTime":1477,"transitTime":0,"waitingTime":0,"walkDistance":1911.8662932276845,"walkLimitExceeded":false,"elevationLost":0.0,"elevationGained":0.0,"transfers":0,"legs":[{"startTime":1522699200000,"endTime":1522700677000,"departureDelay":0,"arrivalDelay":0,"realTime":false,"distance":1911.6990000000003,"pathway":false,"mode":"WALK","route":"","agencyTimeZoneOffset":-14400000,"interlineWithPreviousLeg":false,"from":{"name":"Origin","lon":-71.08157599,"lat":48.44911,"departure":1522699200000,"orig":"","vertexType":"NORMAL"},"to":{"name":"Destination","lon":-71.059915,"lat":48.447474,"arrival":1522700677000,"orig":"","vertexType":"NORMAL"},"legGeometry":{"points":"wuufHpczpLo@TE{A?g@BUDe@H{@DUH]R_ANi@HMl@wALW`@eAd@mAVeAF[BMBKFu@BUBUB[BUBK@KFMFMHKFKHGFEHEZGHELAF?O{AWyCG}@MeB?IEk@Ks@I][gBMs@Ig@Cu@Co@AkA?k@y@Ja@B_@Ce@Q]Ua@g@GIQ]GWCQAq@@e@@e@@If@wD@MHu@R}Ah@mDZ}Bh@{DHm@He@\\gCn@qEZ_CJs@@CLeAd@gDdAgIEGO}@","length":86},"alerts":[{"alertHeaderText":"Unpaved surface"}],"rentedBike":false,"transitLeg":false,"duration":1477.0,"steps":[{"distance":27.586,"relativeDirection":"DEPART","streetName":"path","absoluteDirection":"NORTH","stayOn":false,"area":false,"bogusName":false,"lon":-71.0816896317806,"lat":48.449087594991916,"elevation":[]},{"distance":482.615,"relativeDirection":"RIGHT","streetName":"Rue Saint-Gérard","absoluteDirection":"EAST","stayOn":false,"area":false,"bogusName":false,"lon":-71.0817962,"lat":48.449325400000006,"elevation":[]},{"distance":367.39300000000003,"relativeDirection":"LEFT","streetName":"Rue de l'Aréna","absoluteDirection":"EAST","stayOn":false,"area":false,"bogusName":false,"lon":-71.0764515,"lat":48.4473234,"elevation":[]},{"distance":1004.8749999999999,"relativeDirection":"LEFT","streetName":"Rue Cabot","absoluteDirection":"NORTH","stayOn":false,"area":false,"bogusName":false,"lon":-71.0716385,"lat":48.448087900000004,"elevation":[],"alerts":[{"alertHeaderText":"Unpaved surface"}]},{"distance":29.23,"relativeDirection":"LEFT","streetName":"Rue Cabot","absoluteDirection":"NORTHEAST","stayOn":true,"area":false,"bogusName":false,"lon":-71.0601321,"lat":48.44715,"elevation":[]}]}],"tooSloped":false},{"duration":392,"startTime":1522700447000,"endTime":1522700839000,"walkTime":178,"transitTime":212,"waitingTime":2,"walkDistance":216.44060150083592,"walkLimitExceeded":false,"elevationLost":0.0,"elevationGained":0.0,"transfers":0,"legs":[{"startTime":1522700447000,"endTime":1522700519000,"departureDelay":0,"arrivalDelay":0,"realTime":false,"distance":84.896,"pathway":false,"mode":"WALK","route":"","agencyTimeZoneOffset":-14400000,"interlineWithPreviousLeg":false,"from":{"name":"Origin","lon":-71.08157599,"lat":48.44911,"departure":1522700447000,"orig":"","vertexType":"NORMAL"},"to":{"name":"École Secondaire Charles-Gravel (St-Gérard)","stopId":"1:728","stopCode":"728","lon":-71.08106,"lat":48.449225,"arrival":1522700519000,"departure":1522700520000,"zoneId":"NA","stopIndex":5,"stopSequence":6,"vertexType":"TRANSIT"},"legGeometry":{"points":"wuufHpczpLo@TE{A?g@BU","length":5},"rentedBike":false,"transitLeg":false,"duration":72.0,"steps":[{"distance":27.586,"relativeDirection":"DEPART","streetName":"path","absoluteDirection":"NORTH","stayOn":false,"area":false,"bogusName":false,"lon":-71.0816896317806,"lat":48.449087594991916,"elevation":[]},{"distance":57.31,"relativeDirection":"RIGHT","streetName":"Rue Saint-Gérard","absoluteDirection":"EAST","stayOn":false,"area":false,"bogusName":false,"lon":-71.0817962,"lat":48.449325400000006,"elevation":[]}]},{"startTime":1522700520000,"endTime":1522700732000,"departureDelay":0,"arrivalDelay":0,"realTime":false,"distance":1737.491518363606,"pathway":false,"mode":"BUS","route":"23","agencyName":"Société de Transport du Saguenay","agencyUrl":"http://ville.saguenay.ca/fr/services-aux-citoyens/transport-sts","agencyTimeZoneOffset":-14400000,"routeColor":"FF00FF","routeType":3,"routeId":"1:23","routeTextColor":"FFFFFF","interlineWithPreviousLeg":false,"tripBlockId":"4","headsign":"Terminus Chicoutimi","agencyId":"0","tripId":"1:217242","serviceDate":"20180402","from":{"name":"École Secondaire Charles-Gravel (St-Gérard)","stopId":"1:728","stopCode":"728","lon":-71.08106,"lat":48.449225,"arrival":1522700519000,"departure":1522700520000,"zoneId":"NA","stopIndex":5,"stopSequence":6,"vertexType":"TRANSIT"},"to":{"name":"Comtois / Amiens","stopId":"1:790","stopCode":"790","lon":-71.059239,"lat":48.448251,"arrival":1522700732000,"departure":1522700733000,"zoneId":"NA","stopIndex":13,"stopSequence":14,"vertexType":"TRANSIT"},"legGeometry":{"points":"kwufHh_zpLRoBFe@No@`@gAbCyFNe@Ha@He@Fg@Du@Dg@Hc@Pa@RW\\S`@QZEm@eHM}B?GGi@Is@Ou@Qw@Mo@Kw@ImAGoBAk@aALa@?YEUKc@Yc@_@KOIUGUEWAW?YBqAH_AXeC@IdB_Mh@_EJk@d@kDhAqI`AgHz@oGBU?UAWCWUwAWD]B]AUEoAc@","length":63},"routeShortName":"23","routeLongName":"Côte Verdun via Aréna du Plateau","rentedBike":false,"transitLeg":true,"duration":212.0,"steps":[]},{"startTime":1522700733000,"endTime":1522700839000,"departureDelay":0,"arrivalDelay":0,"realTime":false,"distance":131.454,"pathway":false,"mode":"WALK","route":"","agencyTimeZoneOffset":-14400000,"interlineWithPreviousLeg":false,"from":{"name":"Comtois / Amiens","stopId":"1:790","stopCode":"790","lon":-71.059239,"lat":48.448251,"arrival":1522700732000,"departure":1522700733000,"zoneId":"NA","stopIndex":13,"stopSequence":14,"vertexType":"TRANSIT"},"to":{"name":"Destination","lon":-71.059915,"lat":48.447474,"arrival":1522700839000,"orig":"","vertexType":"NORMAL"},"legGeometry":{"points":"upufH|wupLbA^H?r@Br@QRdA","length":6},"rentedBike":false,"transitLeg":false,"duration":106.0,"steps":[{"distance":103.473,"relativeDirection":"DEPART","streetName":"Rue Comtois","absoluteDirection":"SOUTH","stayOn":false,"area":false,"bogusName":false,"lon":-71.0593436707557,"lat":48.448272300694924,"elevation":[]},{"distance":27.981,"relativeDirection":"RIGHT","streetName":"Rue Cabot","absoluteDirection":"WEST","stayOn":false,"area":false,"bogusName":false,"lon":-71.0594378,"lat":48.4473642,"elevation":[]}]}],"tooSloped":false},{"duration":392,"startTime":1522702247000,"endTime":1522702639000,"walkTime":178,"transitTime":212,"waitingTime":2,"walkDistance":216.44060150083592,"walkLimitExceeded":false,"elevationLost":0.0,"elevationGained":0.0,"transfers":0,"legs":[{"startTime":1522702247000,"endTime":1522702319000,"departureDelay":0,"arrivalDelay":0,"realTime":false,"distance":84.896,"pathway":false,"mode":"WALK","route":"","agencyTimeZoneOffset":-14400000,"interlineWithPreviousLeg":false,"from":{"name":"Origin","lon":-71.08157599,"lat":48.44911,"departure":1522702247000,"orig":"","vertexType":"NORMAL"},"to":{"name":"École Secondaire Charles-Gravel (St-Gérard)","stopId":"1:728","stopCode":"728","lon":-71.08106,"lat":48.449225,"arrival":1522702319000,"departure":1522702320000,"zoneId":"NA","stopIndex":5,"stopSequence":6,"vertexType":"TRANSIT"},"legGeometry":{"points":"wuufHpczpLo@TE{A?g@BU","length":5},"rentedBike":false,"transitLeg":false,"duration":72.0,"steps":[{"distance":27.586,"relativeDirection":"DEPART","streetName":"path","absoluteDirection":"NORTH","stayOn":false,"area":false,"bogusName":false,"lon":-71.0816896317806,"lat":48.449087594991916,"elevation":[]},{"distance":57.31,"relativeDirection":"RIGHT","streetName":"Rue Saint-Gérard","absoluteDirection":"EAST","stayOn":false,"area":false,"bogusName":false,"lon":-71.0817962,"lat":48.449325400000006,"elevation":[]}]},{"startTime":1522702320000,"endTime":1522702532000,"departureDelay":0,"arrivalDelay":0,"realTime":false,"distance":1737.491518363606,"pathway":false,"mode":"BUS","route":"23","agencyName":"Société de Transport du Saguenay","agencyUrl":"http://ville.saguenay.ca/fr/services-aux-citoyens/transport-sts","agencyTimeZoneOffset":-14400000,"routeColor":"FF00FF","routeType":3,"routeId":"1:23","routeTextColor":"FFFFFF","interlineWithPreviousLeg":false,"tripBlockId":"5","headsign":"Terminus Chicoutimi","agencyId":"0","tripId":"1:217270","serviceDate":"20180402","from":{"name":"École Secondaire Charles-Gravel (St-Gérard)","stopId":"1:728","stopCode":"728","lon":-71.08106,"lat":48.449225,"arrival":1522702319000,"departure":1522702320000,"zoneId":"NA","stopIndex":5,"stopSequence":6,"vertexType":"TRANSIT"},"to":{"name":"Comtois / Amiens","stopId":"1:790","stopCode":"790","lon":-71.059239,"lat":48.448251,"arrival":1522702532000,"departure":1522702533000,"zoneId":"NA","stopIndex":13,"stopSequence":14,"vertexType":"TRANSIT"},"legGeometry":{"points":"kwufHh_zpLRoBFe@No@`@gAbCyFNe@Ha@He@Fg@Du@Dg@Hc@Pa@RW\\S`@QZEm@eHM}B?GGi@Is@Ou@Qw@Mo@Kw@ImAGoBAk@aALa@?YEUKc@Yc@_@KOIUGUEWAW?YBqAH_AXeC@IdB_Mh@_EJk@d@kDhAqI`AgHz@oGBU?UAWCWUwAWD]B]AUEoAc@","length":63},"routeShortName":"23","routeLongName":"Côte Verdun via Aréna du Plateau","rentedBike":false,"transitLeg":true,"duration":212.0,"steps":[]},{"startTime":1522702533000,"endTime":1522702639000,"departureDelay":0,"arrivalDelay":0,"realTime":false,"distance":131.454,"pathway":false,"mode":"WALK","route":"","agencyTimeZoneOffset":-14400000,"interlineWithPreviousLeg":false,"from":{"name":"Comtois / Amiens","stopId":"1:790","stopCode":"790","lon":-71.059239,"lat":48.448251,"arrival":1522702532000,"departure":1522702533000,"zoneId":"NA","stopIndex":13,"stopSequence":14,"vertexType":"TRANSIT"},"to":{"name":"Destination","lon":-71.059915,"lat":48.447474,"arrival":1522702639000,"orig":"","vertexType":"NORMAL"},"legGeometry":{"points":"upufH|wupLbA^H?r@Br@QRdA","length":6},"rentedBike":false,"transitLeg":false,"duration":106.0,"steps":[{"distance":103.473,"relativeDirection":"DEPART","streetName":"Rue Comtois","absoluteDirection":"SOUTH","stayOn":false,"area":false,"bogusName":false,"lon":-71.0593436707557,"lat":48.448272300694924,"elevation":[]},{"distance":27.981,"relativeDirection":"RIGHT","streetName":"Rue Cabot","absoluteDirection":"WEST","stayOn":false,"area":false,"bogusName":false,"lon":-71.0594378,"lat":48.4473642,"elevation":[]}]}],"tooSloped":false}]},"debugOutput":{"precalculationTime":12,"pathCalculationTime":17,"pathTimes":[9,6,2],"renderingTime":0,"totalTime":29,"timedOut":false},"elevationMetadata":{"ellipsoidToGeoidDifference":-28.885904201182168,"geoidElevation":false}}