{"requestParameters":{"date":"2018/04/02","walkSpeed":"1.33","walkReluctance":"2.0","fromPlace":"48.408664,-71.048969","maxWalkDistance":"3000","waitReluctance":"1.0","carSpeed":"33","numItineraries":"3","waitAtBeginningFactor":"0.4","mode":"TRANSIT,WALK","ignoreRealtimeUpdates":"false","stairsReluctance":"2.0","toPlace":"48.408285,-71.051148","time":"11:40:00"},"plan":{"date":1522683600000,"from":{"name":"Origin","lon":-71.048969,"lat":48.408664,"orig":"","vertexType":"NORMAL"},"to":{"name":"Destination","lon":-71.051148,"lat":48.408285,"orig":"","vertexType":"NORMAL"},"itineraries":[{"duration":202,"startTime":1522683600000,"endTime":1522683802000,"walkTime":202,"transitTime":0,"waitingTime":0,"walkDistance":260.1743383447244,"walkLimitExceeded":false,"elevationLost":0.0,"elevationGained":0.0,"transfers":0,"legs":[{"startTime":1522683600000,"endTime":1522683802000,"departureDelay":0,"arrivalDelay":0,"realTime":false,"distance":260.139,"pathway":false,"mode":"WALK","route":"","agencyTimeZoneOffset":-14400000,"interlineWithPreviousLeg":false,"from":{"name":"Origin","lon":-71.048969,"lat":48.408664,"departure":1522683600000,"orig":"","vertexType":"NORMAL"},"to":{"name":"Destination","lon":-71.051148,"lat":48.408285,"arrival":1522683802000,"orig":"","vertexType":"NORMAL"},"legGeometry":{"points":"yxmfH~uspLtDhBq@rDe@~CMPKE","length":6},"rentedBike":false,"transitLeg":false,"duration":202.0,"steps":[{"distance":108.822,"relativeDirection":"DEPART","streetName":"Rue Des Roitelets","absoluteDirection":"SOUTH","stayOn":false,"area":false,"bogusName":false,"lon":-71.04879348375177,"lat":48.408619162095704,"elevation":[]},{"distance":151.317,"relativeDirection":"RIGHT","streetName":"Rue Lorenzo-Genest","absoluteDirection":"WEST","stayOn":false,"area":false,"bogusName":false,"lon":-71.049323,"lat":48.4077058,"elevation":[]}]}],"tooSloped":false}]},"debugOutput":{"precalculationTime":49,"pathCalculationTime":18,"pathTimes":[0,16,2],"renderingTime":0,"totalTime":67,"timedOut":false},"elevationMetadata":{"ellipsoidToGeoidDifference":-28.885904201182168,"geoidElevation":false}}