{"requestParameters":{"date":"2018/04/02","walkSpeed":"1.33","walkReluctance":"2.0","fromPlace":"48.401256,-71.085016","maxWalkDistance":"3000","waitReluctance":"1.0","carSpeed":"33","numItineraries":"3","waitAtBeginningFactor":"0.4","mode":"TRANSIT,WALK","ignoreRealtimeUpdates":"false","stairsReluctance":"2.0","toPlace":"48.410458,-71.047752","time":"7:30:00"},"plan":{"date":1522668600000,"from":{"name":"Origin","lon":-71.085016,"lat":48.401256,"orig":"","vertexType":"NORMAL"},"to":{"name":"Destination","lon":-71.047752,"lat":48.410458,"orig":"","vertexType":"NORMAL"},"itineraries":[{"duration":1731,"startTime":1522668889000,"endTime":1522670620000,"walkTime":1252,"transitTime":477,"waitingTime":2,"walkDistance":1592.6892631496585,"walkLimitExceeded":false,"elevationLost":0.0,"elevationGained":0.0,"transfers":0,"legs":[{"startTime":1522668889000,"endTime":1522669169000,"departureDelay":0,"arrivalDelay":0,"realTime":false,"distance":339.595,"pathway":false,"mode":"WALK","route":"","agencyTimeZoneOffset":-14400000,"interlineWithPreviousLeg":false,"from":{"name":"Origin","lon":-71.085016,"lat":48.401256,"departure":1522668889000,"orig":"","vertexType":"NORMAL"},"to":{"name":"boul. Barrette / passerelle rue Marcel-Portal","stopId":"1:90","stopCode":"90","lon":-71.085149,"lat":48.399287,"arrival":1522669169000,"departure":1522669170000,"zoneId":"NA","stopIndex":31,"stopSequence":32,"vertexType":"TRANSIT"},"legGeometry":{"points":"cllfHnwzpL@CBiAZYxAu@NjA?P~@Ct@^l@`@TcAv@l@RZRRLNCJ","length":16},"rentedBike":false,"transitLeg":false,"duration":280.0,"steps":[{"distance":100.525,"relativeDirection":"DEPART","streetName":"Rue Romain Gary","absoluteDirection":"EAST","stayOn":false,"area":false,"bogusName":false,"lon":-71.08487524931819,"lat":48.40146171011184,"elevation":[]},{"distance":36.096,"relativeDirection":"RIGHT","streetName":"Rue Yves Thériault","absoluteDirection":"WEST","stayOn":false,"area":false,"bogusName":false,"lon":-71.0840893,"lat":48.400847600000006,"elevation":[]},{"distance":96.725,"relativeDirection":"LEFT","streetName":"Rue Boris Vian","absoluteDirection":"SOUTH","stayOn":false,"area":false,"bogusName":false,"lon":-71.0845591,"lat":48.4007658,"elevation":[]},{"distance":28.015,"relativeDirection":"LEFT","streetName":"Rue Jean-Paul Sartre","absoluteDirection":"SOUTHEAST","stayOn":false,"area":false,"bogusName":false,"lon":-71.0848672,"lat":48.3999413,"elevation":[]},{"distance":73.29599999999999,"relativeDirection":"RIGHT","streetName":"path","absoluteDirection":"SOUTHWEST","stayOn":false,"area":false,"bogusName":true,"lon":-71.0845255,"lat":48.3998317,"elevation":[]},{"distance":4.938,"relativeDirection":"RIGHT","streetName":"bike path","absoluteDirection":"NORTHWEST","stayOn":true,"area":false,"bogusName":true,"lon":-71.08507540000001,"lat":48.3992865,"elevation":[]}]},{"startTime":1522669170000,"endTime":1522669260000,"departureDelay":0,"arrivalDelay":0,"realTime":false,"distance":1328.7038023955338,"pathway":false,"mode":"BUS","route":"14","agencyName":"Société de Transport du Saguenay","agencyUrl":"http://ville.saguenay.ca/fr/services-aux-citoyens/transport-sts","agencyTimeZoneOffset":-14400000,"routeColor":"C0C000","routeType":3,"routeId":"1:14","routeTextColor":"000000","interlineWithPreviousLeg":false,"tripBlockId":"32","headsign":"Talbot / Barrette","agencyId":"0","tripId":"1:218148","serviceDate":"20180402","from":{"name":"boul. Barrette / passerelle rue Marcel-Portal","stopId":"1:90","stopCode":"90","lon":-71.085149,"lat":48.399287,"arrival":1522669169000,"departure":1522669170000,"zoneId":"NA","stopIndex":31,"stopSequence":32,"vertexType":"TRANSIT"},"to":{"name":"Roitelets / Sapins","stopId":"1:1543","stopCode":"1543","lon":-71.069553,"lat":48.393375,"arrival":1522669260000,"departure":1522669260000,"zoneId":"NA","stopIndex":35,"stopSequence":36,"vertexType":"TRANSIT"},"legGeometry":{"points":"e_lfHvxzpLj@oCvEoSl@_CxCmLjAeFpCeKrByHfAqCvH_SLa@","length":11},"routeShortName":"14","routeLongName":"Coopérative","rentedBike":false,"transitLeg":true,"duration":90.0,"steps":[]},{"startTime":1522669260000,"endTime":1522669647000,"departureDelay":0,"arrivalDelay":0,"realTime":false,"distance":2602.9367627755005,"pathway":false,"mode":"BUS","route":"15","agencyName":"Société de Transport du Saguenay","agencyUrl":"http://ville.saguenay.ca/fr/services-aux-citoyens/transport-sts","agencyTimeZoneOffset":-14400000,"routeColor":"FF00FF","routeType":3,"routeId":"1:15","routeTextColor":"FFFFFF","interlineWithPreviousLeg":true,"tripBlockId":"32","headsign":"Terminus Chicoutimi","agencyId":"0","tripId":"1:218149","serviceDate":"20180402","from":{"name":"Roitelets / Sapins","stopId":"1:1543","stopCode":"1543","lon":-71.069553,"lat":48.393375,"arrival":1522669260000,"departure":1522669260000,"zoneId":"NA","stopIndex":0,"stopSequence":1,"vertexType":"TRANSIT"},"to":{"name":"Engoulevents / Sternes","stopId":"1:1568","stopCode":"1568","lon":-71.050864,"lat":48.400594,"arrival":1522669647000,"departure":1522669648000,"zoneId":"NA","stopIndex":10,"stopSequence":11,"vertexType":"TRANSIT"},"legGeometry":{"points":"_zjfHfwwpLx@}BHa@NaADq@@y@Cy@I{@Ka@O[Sg@c@mAWwAMyA?EC]?wABuABmFB{@BmDFuH@i@F[FsC@c@TuGEGVsHPuDLuBXsFDoA?W@]Cu@GcAKu@Q_ASo@a@y@a@o@MOUUeCqBiDsDqE{EiAcAcB_AqBgA_AQaBSaBG_@Bu@FG?h@fNKnDpCfBkAzDgA}@y@q@sDy@","length":63},"routeShortName":"15","routeLongName":"Term. Chic / Costco","rentedBike":false,"transitLeg":true,"duration":387.0,"steps":[]},{"startTime":1522669648000,"endTime":1522670620000,"departureDelay":0,"arrivalDelay":0,"realTime":false,"distance":1252.8389999999997,"pathway":false,"mode":"WALK","route":"","agencyTimeZoneOffset":-14400000,"interlineWithPreviousLeg":false,"from":{"name":"Engoulevents / Sternes","stopId":"1:1568","stopCode":"1568","lon":-71.050864,"lat":48.400594,"arrival":1522669647000,"departure":1522669648000,"zoneId":"NA","stopIndex":10,"stopSequence":11,"vertexType":"TRANSIT"},"to":{"name":"Destination","lon":-71.047752,"lat":48.410458,"arrival":1522670620000,"orig":"","vertexType":"NORMAL"},"legGeometry":{"points":"uflfHjctpLA?}@Eg@E}ANq@TUF_@JkEhAsBl@OFe@L_@DgA?uAK}@M}@Cq@Dm@Pu@\\{@qEGo@AGAKEU?iAGUMYW]mB}@AAm@WqG}CqAq@GCk@Y_Bw@KEGEYK","length":40},"rentedBike":false,"transitLeg":false,"duration":972.0,"steps":[{"distance":152.28900000000002,"relativeDirection":"DEPART","streetName":"Rue des Engoulevents","absoluteDirection":"NORTH","stayOn":false,"area":false,"bogusName":false,"lon":-71.05093708693188,"lat":48.40059768260656,"elevation":[]},{"distance":494.33299999999997,"relativeDirection":"CONTINUE","streetName":"Rue des Champs-Élysées","absoluteDirection":"NORTH","stayOn":false,"area":false,"bogusName":false,"lon":-71.0511074,"lat":48.401948700000005,"elevation":[]},{"distance":146.36399999999998,"relativeDirection":"RIGHT","streetName":"Rue Émile-Girardin","absoluteDirection":"NORTHEAST","stayOn":false,"area":false,"bogusName":false,"lon":-71.05202630000001,"lat":48.4062974,"elevation":[]},{"distance":39.358,"relativeDirection":"SLIGHTLY_LEFT","streetName":"link","absoluteDirection":"NORTHEAST","stayOn":false,"area":false,"bogusName":true,"lon":-71.0501541,"lat":48.406688800000005,"elevation":[]},{"distance":420.49500000000006,"relativeDirection":"SLIGHTLY_LEFT","streetName":"Rue Des Roitelets","absoluteDirection":"NORTH","stayOn":false,"area":false,"bogusName":false,"lon":-71.0497603,"lat":48.406919900000005,"elevation":[]}]}],"tooSloped":false},{"duration":2158,"startTime":1522669149000,"endTime":1522671307000,"walkTime":329,"transitTime":1347,"waitingTime":482,"walkDistance":404.28317292687217,"walkLimitExceeded":false,"elevationLost":0.0,"elevationGained":0.0,"transfers":1,"legs":[{"startTime":1522669149000,"endTime":1522669412000,"departureDelay":0,"arrivalDelay":0,"realTime":false,"distance":319.87,"pathway":false,"mode":"WALK","route":"","agencyTimeZoneOffset":-14400000,"interlineWithPreviousLeg":false,"from":{"name":"Origin","lon":-71.085016,"lat":48.401256,"departure":1522669149000,"orig":"","vertexType":"NORMAL"},"to":{"name":"boul. Barrette passerelle J.Paul Sartre","stopId":"1:1898","stopCode":"1898","lon":-71.084773,"lat":48.399467,"arrival":1522669412000,"departure":1522669413000,"zoneId":"NA","stopIndex":4,"stopSequence":5,"vertexType":"TRANSIT"},"legGeometry":{"points":"cllfHnwzpL@CBiAZYxAu@NjA?P~@Ct@^l@`@TcAv@l@RZDQ","length":14},"rentedBike":false,"transitLeg":false,"duration":263.0,"steps":[{"distance":100.525,"relativeDirection":"DEPART","streetName":"Rue Romain Gary","absoluteDirection":"EAST","stayOn":false,"area":false,"bogusName":false,"lon":-71.08487524931819,"lat":48.40146171011184,"elevation":[]},{"distance":36.096,"relativeDirection":"RIGHT","streetName":"Rue Yves Thériault","absoluteDirection":"WEST","stayOn":false,"area":false,"bogusName":false,"lon":-71.0840893,"lat":48.400847600000006,"elevation":[]},{"distance":96.725,"relativeDirection":"LEFT","streetName":"Rue Boris Vian","absoluteDirection":"SOUTH","stayOn":false,"area":false,"bogusName":false,"lon":-71.0845591,"lat":48.4007658,"elevation":[]},{"distance":28.015,"relativeDirection":"LEFT","streetName":"Rue Jean-Paul Sartre","absoluteDirection":"SOUTHEAST","stayOn":false,"area":false,"bogusName":false,"lon":-71.0848672,"lat":48.3999413,"elevation":[]},{"distance":50.8,"relativeDirection":"RIGHT","streetName":"path","absoluteDirection":"SOUTHWEST","stayOn":false,"area":false,"bogusName":true,"lon":-71.0845255,"lat":48.3998317,"elevation":[]},{"distance":7.709,"relativeDirection":"LEFT","streetName":"Boulevard Barrette","absoluteDirection":"SOUTHEAST","stayOn":false,"area":false,"bogusName":false,"lon":-71.0848982,"lat":48.3994511,"elevation":[]}]},{"startTime":1522669413000,"endTime":1522670460000,"departureDelay":0,"arrivalDelay":0,"realTime":false,"distance":6611.2806362991705,"pathway":false,"mode":"BUS","route":"14","agencyName":"Société de Transport du Saguenay","agencyUrl":"http://ville.saguenay.ca/fr/services-aux-citoyens/transport-sts","agencyTimeZoneOffset":-14400000,"routeColor":"C0C000","routeType":3,"routeId":"1:14","routeTextColor":"000000","interlineWithPreviousLeg":false,"tripBlockId":"33","headsign":"Terminus Chicoutimi","agencyId":"0","tripId":"1:218174","serviceDate":"20180402","from":{"name":"boul. Barrette passerelle J.Paul Sartre","stopId":"1:1898","stopCode":"1898","lon":-71.084773,"lat":48.399467,"arrival":1522669412000,"departure":1522669413000,"zoneId":"NA","stopIndex":4,"stopSequence":5,"vertexType":"TRANSIT"},"to":{"name":"Terminus UQAC","stopId":"1:1670","stopCode":"1670","lon":-71.053369,"lat":48.420903,"arrival":1522670460000,"departure":1522670940000,"zoneId":"NA","stopIndex":29,"stopSequence":30,"vertexType":"TRANSIT"},"legGeometry":{"points":"y~kfHlwzpLwGd\\aDxOdFtFhCtCdDY|F_On@aB`B_GNoBvAyT|@sNuAyAuF}F}AaB_BkAC@qC\\gAWiBwBiKgMiCwEgEyHCGy@uB}@rAa@nAc@lFEf@mGvUYfAqCs@ICMCqFmDc@s@mAkBuEoESUgAhDiAfD}@zDyAcA_@Um@U{AWgB_Au@s@EEsBkCqFgF{IiI][aBhE}@}@oBmBwE{EwE{Ej@mBZeAa@SyEQg@CPcALuCx@{b@t@{[XoDd@sBl@iB~@gA`G{F{A{D_@sBFqDOq@iG{F","length":77},"routeShortName":"14","routeLongName":"Coopérative","rentedBike":false,"transitLeg":true,"duration":1047.0,"steps":[]},{"startTime":1522670940000,"endTime":1522671240000,"departureDelay":0,"arrivalDelay":0,"realTime":false,"distance":1387.1470604312278,"pathway":false,"mode":"BUS","route":"175","agencyName":"Société de Transport du Saguenay","agencyUrl":"http://ville.saguenay.ca/fr/services-aux-citoyens/transport-sts","agencyTimeZoneOffset":-14400000,"routeColor":"FF00FF","routeType":3,"routeId":"1:175","routeTextColor":"FFFFFF","interlineWithPreviousLeg":false,"tripBlockId":"79","headsign":"Costco","agencyId":"0","tripId":"1:218649","serviceDate":"20180402","from":{"name":"Terminus UQAC","stopId":"1:1670","stopCode":"1670","lon":-71.053369,"lat":48.420903,"arrival":1522670460000,"departure":1522670940000,"zoneId":"NA","stopIndex":11,"stopSequence":12,"vertexType":"TRANSIT"},"to":{"name":"Sûreté du Québec (Roitelets / Lorenzo-Genest)","stopId":"1:58","stopCode":"58","lon":-71.048311,"lat":48.40979,"arrival":1522671240000,"departure":1522671241000,"zoneId":"NA","stopIndex":15,"stopSequence":16,"vertexType":"TRANSIT"},"legGeometry":{"points":"sepfHtrtpL`A~@Xw@~D~DPxFZtA~ApE`N{LpFmEb@[ROl@[vDQXKfA[|@q@fAsBlEmMr@sBhCsKz@dAjB|@","length":22},"routeShortName":"175","routeLongName":"Term. Chic / Costco","rentedBike":false,"transitLeg":true,"duration":300.0,"steps":[]},{"startTime":1522671241000,"endTime":1522671307000,"departureDelay":0,"arrivalDelay":0,"realTime":false,"distance":84.244,"pathway":false,"mode":"WALK","route":"","agencyTimeZoneOffset":-14400000,"interlineWithPreviousLeg":false,"from":{"name":"Sûreté du Québec (Roitelets / Lorenzo-Genest)","stopId":"1:58","stopCode":"58","lon":-71.048311,"lat":48.40979,"arrival":1522671240000,"departure":1522671241000,"zoneId":"NA","stopIndex":15,"stopSequence":16,"vertexType":"TRANSIT"},"to":{"name":"Destination","lon":-71.047752,"lat":48.410458,"arrival":1522671307000,"orig":"","vertexType":"NORMAL"},"legGeometry":{"points":"{_nfHzqspL_Bw@KEGEYK","length":5},"rentedBike":false,"transitLeg":false,"duration":66.0,"steps":[{"distance":84.244,"relativeDirection":"DEPART","streetName":"Rue Des Roitelets","absoluteDirection":"NORTH","stayOn":false,"area":false,"bogusName":false,"lon":-71.04813827023435,"lat":48.409745631017636,"elevation":[]}]}],"tooSloped":false},{"duration":1895,"startTime":1522670352000,"endTime":1522672247000,"walkTime":1040,"transitTime":853,"waitingTime":2,"walkDistance":1312.9907969821948,"walkLimitExceeded":false,"elevationLost":0.0,"elevationGained":0.0,"transfers":0,"legs":[{"startTime":1522670352000,"endTime":1522670953000,"departureDelay":0,"arrivalDelay":0,"realTime":false,"distance":743.5060000000001,"pathway":false,"mode":"WALK","route":"","agencyTimeZoneOffset":-14400000,"interlineWithPreviousLeg":false,"from":{"name":"Origin","lon":-71.085016,"lat":48.401256,"departure":1522670352000,"orig":"","vertexType":"NORMAL"},"to":{"name":"Malraux / Rabelais","stopId":"1:2111","stopCode":"2111","lon":-71.085623,"lat":48.396343,"arrival":1522670953000,"departure":1522670954000,"zoneId":"NA","stopIndex":12,"stopSequence":13,"vertexType":"TRANSIT"},"legGeometry":{"points":"cllfHnwzpL@CBiAZYxAu@NjA?P~@Ct@^l@`@TcAv@l@RZRRLNhAr@EPv@Vd@\\d@\\BQPUTBnBd@pA\\xCp@LiB@M","length":28},"rentedBike":false,"transitLeg":false,"duration":601.0,"steps":[{"distance":100.525,"relativeDirection":"DEPART","streetName":"Rue Romain Gary","absoluteDirection":"EAST","stayOn":false,"area":false,"bogusName":false,"lon":-71.08487524931819,"lat":48.40146171011184,"elevation":[]},{"distance":36.096,"relativeDirection":"RIGHT","streetName":"Rue Yves Thériault","absoluteDirection":"WEST","stayOn":false,"area":false,"bogusName":false,"lon":-71.0840893,"lat":48.400847600000006,"elevation":[]},{"distance":96.725,"relativeDirection":"LEFT","streetName":"Rue Boris Vian","absoluteDirection":"SOUTH","stayOn":false,"area":false,"bogusName":false,"lon":-71.0845591,"lat":48.4007658,"elevation":[]},{"distance":28.015,"relativeDirection":"LEFT","streetName":"Rue Jean-Paul Sartre","absoluteDirection":"SOUTHEAST","stayOn":false,"area":false,"bogusName":false,"lon":-71.0848672,"lat":48.3999413,"elevation":[]},{"distance":205.885,"relativeDirection":"RIGHT","streetName":"path","absoluteDirection":"SOUTHWEST","stayOn":false,"area":false,"bogusName":true,"lon":-71.0845255,"lat":48.3998317,"elevation":[]},{"distance":231.00600000000003,"relativeDirection":"LEFT","streetName":"Rue Montaigne","absoluteDirection":"SOUTHEAST","stayOn":false,"area":false,"bogusName":false,"lon":-71.08584950000001,"lat":48.3982888,"elevation":[]},{"distance":45.254,"relativeDirection":"LEFT","streetName":"Rue Malraux","absoluteDirection":"EAST","stayOn":false,"area":false,"bogusName":false,"lon":-71.08625400000001,"lat":48.396321,"elevation":[]}]},{"startTime":1522670954000,"endTime":1522671807000,"departureDelay":0,"arrivalDelay":0,"realTime":false,"distance":5051.029174852059,"pathway":false,"mode":"BUS","route":"205S","agencyName":"Société de Transport du Saguenay","agencyUrl":"http://ville.saguenay.ca/fr/services-aux-citoyens/transport-sts","agencyTimeZoneOffset":-14400000,"routeColor":"8B0000","routeType":3,"routeId":"1:205S","routeTextColor":"FFFFFF","interlineWithPreviousLeg":false,"tripBlockId":"49","headsign":"Séminaire","agencyId":"0","tripId":"1:218411","serviceDate":"20180402","from":{"name":"Malraux / Rabelais","stopId":"1:2111","stopCode":"2111","lon":-71.085623,"lat":48.396343,"arrival":1522670953000,"departure":1522670954000,"zoneId":"NA","stopIndex":12,"stopSequence":13,"vertexType":"TRANSIT"},"to":{"name":"boul. Université / Thérèse Casgrain","stopId":"1:83","stopCode":"83","lon":-71.053451,"lat":48.413578,"arrival":1522671807000,"departure":1522671808000,"zoneId":"NA","stopIndex":23,"stopSequence":24,"vertexType":"TRANSIT"},"legGeometry":{"points":"skkfHh|zpLUdCkCs@cB]?NcD|OSf@s@tAUj@Qh@PPRVJPDHNZV`@tDtEyBzFiCvGKPMJOBqABWASGQQcCqCiFcGsBwB|BiGRm@Nq@lAoG@IAICIEGoPcLkDqBa@Qm@Oa@AGyBGoAa@oDo@qDS_Ba@kEG[MWg@_@IHULQAw@M_A_@IIKI[[YWaBy@aAu@o@m@KK]a@}A_CcD{C[[eCsBoBmB]q@WeBy@wMIUwB{D{AcDsEmKUCrDoKoByB}DcE}A_BoAmAk@o@aC_CkIkIaJaJWWuB_C\\{AZkANe@P]^s@`@k@fAgAfDwCtC_CxQaPRQHG^Q\\Mb@I~CILC","length":106},"routeShortName":"205S","routeLongName":"Séminaire - Bégin/Malraux","rentedBike":false,"transitLeg":true,"duration":853.0,"steps":[]},{"startTime":1522671808000,"endTime":1522672247000,"departureDelay":0,"arrivalDelay":0,"realTime":false,"distance":569.1659999999999,"pathway":false,"mode":"WALK","route":"","agencyTimeZoneOffset":-14400000,"interlineWithPreviousLeg":false,"from":{"name":"boul. Université / Thérèse Casgrain","stopId":"1:83","stopCode":"83","lon":-71.053451,"lat":48.413578,"arrival":1522671807000,"departure":1522671808000,"zoneId":"NA","stopIndex":23,"stopSequence":24,"vertexType":"TRANSIT"},"to":{"name":"Destination","lon":-71.047752,"lat":48.410458,"arrival":1522672247000,"orig":"","vertexType":"NORMAL"},"legGeometry":{"points":"{wnfHprtpL~@WfAaAp@mAL[Nc@fA}CJ]Na@|AmETo@xBeHF_@ReAHe@HBVJ","length":17},"rentedBike":false,"transitLeg":false,"duration":439.0,"steps":[{"distance":549.314,"relativeDirection":"DEPART","streetName":"Boulevard de l'Université","absoluteDirection":"SOUTH","stayOn":false,"area":false,"bogusName":false,"lon":-71.053365,"lat":48.413586,"elevation":[]},{"distance":19.852,"relativeDirection":"RIGHT","streetName":"Rue Des Roitelets","absoluteDirection":"SOUTH","stayOn":false,"area":false,"bogusName":false,"lon":-71.0476524,"lat":48.4106242,"elevation":[]}]}],"tooSloped":false}]},"debugOutput":{"precalculationTime":37,"pathCalculationTime":34,"pathTimes":[20,7,7],"renderingTime":0,"totalTime":71,"timedOut":false},"elevationMetadata":{"ellipsoidToGeoidDifference":-28.885904201182168,"geoidElevation":false}}