{"requestParameters":{"date":"2018/04/02","walkSpeed":"1.33","walkReluctance":"2.0","fromPlace":"48.423148,-71.052406","maxWalkDistance":"3000","waitReluctance":"1.0","carSpeed":"33","numItineraries":"3","waitAtBeginningFactor":"0.4","mode":"TRANSIT,WALK","ignoreRealtimeUpdates":"false","stairsReluctance":"2.0","toPlace":"48.426574,-71.052185","time":"17:35:00"},"plan":{"date":1522704900000,"from":{"name":"Origin","lon":-71.052406,"lat":48.423148,"orig":"","vertexType":"NORMAL"},"to":{"name":"Destination","lon":-71.052185,"lat":48.426574,"orig":"","vertexType":"NORMAL"},"itineraries":[{"duration":488,"startTime":1522704900000,"endTime":1522705388000,"walkTime":488,"transitTime":0,"waitingTime":0,"walkDistance":614.6923458601977,"walkLimitExceeded":false,"elevationLost":0.0,"elevationGained":0.0,"transfers":0,"legs":[{"startTime":1522704900000,"endTime":1522705388000,"departureDelay":0,"arrivalDelay":0,"realTime":false,"distance":614.554,"pathway":false,"mode":"WALK","route":"","agencyTimeZoneOffset":-14400000,"interlineWithPreviousLeg":false,"from":{"name":"Origin","lon":-71.052406,"lat":48.423148,"departure":1522704900000,"orig":"","vertexType":"NORMAL"},"to":{"name":"Destination","lon":-71.052185,"lat":48.426574,"arrival":1522705388000,"orig":"","vertexType":"NORMAL"},"legGeometry":{"points":"qspfHpltpL?g@CcBIUMc@[Q]QXcCKGe@[KIMGq@YCEO^i@pCa@bD?FYKMEYCWNWVILMPo@QuEi@","length":27},"rentedBike":false,"transitLeg":false,"duration":488.0,"steps":[{"distance":162.836,"relativeDirection":"DEPART","streetName":"service road","absoluteDirection":"EAST","stayOn":false,"area":false,"bogusName":false,"lon":-71.05240568397582,"lat":48.423135724671475,"elevation":[]},{"distance":78.756,"relativeDirection":"LEFT","streetName":"road","absoluteDirection":"NORTHEAST","stayOn":false,"area":false,"bogusName":true,"lon":-71.0505725,"lat":48.4234394,"elevation":[]},{"distance":253.13899999999998,"relativeDirection":"LEFT","streetName":"path","absoluteDirection":"NORTHWEST","stayOn":true,"area":false,"bogusName":true,"lon":-71.0501431,"lat":48.4240852,"elevation":[]},{"distance":119.823,"relativeDirection":"CONTINUE","streetName":"Rue du Séminaire","absoluteDirection":"NORTH","stayOn":false,"area":false,"bogusName":false,"lon":-71.05205670000001,"lat":48.4254766,"elevation":[]}]}],"tooSloped":false},{"duration":429,"startTime":1522706353000,"endTime":1522706782000,"walkTime":308,"transitTime":119,"waitingTime":2,"walkDistance":393.62795488457357,"walkLimitExceeded":false,"elevationLost":0.0,"elevationGained":0.0,"transfers":0,"legs":[{"startTime":1522706353000,"endTime":1522706533000,"departureDelay":0,"arrivalDelay":0,"realTime":false,"distance":229.888,"pathway":false,"mode":"WALK","route":"","agencyTimeZoneOffset":-14400000,"interlineWithPreviousLeg":false,"from":{"name":"Origin","lon":-71.052406,"lat":48.423148,"departure":1522706353000,"orig":"","vertexType":"NORMAL"},"to":{"name":"Cégep de Chicoutimi (voie réservée)","stopId":"1:65","stopCode":"65","lon":-71.054799,"lat":48.423007,"arrival":1522706533000,"departure":1522706534000,"zoneId":"NA","stopIndex":16,"stopSequence":17,"vertexType":"TRANSIT"},"legGeometry":{"points":"qspfHpltpL?n@CVWrB~A^_@hAUt@@z@Hn@BR","length":10},"rentedBike":false,"transitLeg":false,"duration":180.0,"steps":[{"distance":71.52,"relativeDirection":"DEPART","streetName":"service road","absoluteDirection":"WEST","stayOn":false,"area":false,"bogusName":false,"lon":-71.05240568397582,"lat":48.423135724671475,"elevation":[]},{"distance":54.189,"relativeDirection":"LEFT","streetName":"path","absoluteDirection":"SOUTH","stayOn":false,"area":false,"bogusName":true,"lon":-71.05334280000001,"lat":48.4232749,"elevation":[]},{"distance":104.179,"relativeDirection":"RIGHT","streetName":"bike path","absoluteDirection":"NORTHWEST","stayOn":true,"area":false,"bogusName":true,"lon":-71.053503,"lat":48.4227993,"elevation":[]}]},{"startTime":1522706534000,"endTime":1522706653000,"departureDelay":0,"arrivalDelay":0,"realTime":false,"distance":528.1389100266687,"pathway":false,"mode":"BUS","route":"175","agencyName":"Société de Transport du Saguenay","agencyUrl":"http://ville.saguenay.ca/fr/services-aux-citoyens/transport-sts","agencyTimeZoneOffset":-14400000,"routeColor":"FF00FF","routeType":3,"routeId":"1:175","routeTextColor":"FFFFFF","interlineWithPreviousLeg":false,"tripBlockId":"9","headsign":"Terminus Chicoutimi","agencyId":"0","tripId":"1:217414","serviceDate":"20180402","from":{"name":"Cégep de Chicoutimi (voie réservée)","stopId":"1:65","stopCode":"65","lon":-71.054799,"lat":48.423007,"arrival":1522706533000,"departure":1522706534000,"zoneId":"NA","stopIndex":16,"stopSequence":17,"vertexType":"TRANSIT"},"to":{"name":"Jacques-Cartier / Séminaire","stopId":"1:1918","stopCode":"1918","lon":-71.052669,"lat":48.425403,"arrival":1522706653000,"departure":1522706654000,"zoneId":"NA","stopIndex":19,"stopSequence":20,"vertexType":"TRANSIT"},"legGeometry":{"points":"grpfHf{tpLf@|C[dCuAfB]xAs@OmCmCmEkE]a@g@i@ZiGTmE","length":12},"routeShortName":"175","routeLongName":"Term. Chic / Costco","rentedBike":false,"transitLeg":true,"duration":119.0,"steps":[]},{"startTime":1522706654000,"endTime":1522706782000,"departureDelay":0,"arrivalDelay":0,"realTime":false,"distance":163.658,"pathway":false,"mode":"WALK","route":"","agencyTimeZoneOffset":-14400000,"interlineWithPreviousLeg":false,"from":{"name":"Jacques-Cartier / Séminaire","stopId":"1:1918","stopCode":"1918","lon":-71.052669,"lat":48.425403,"arrival":1522706653000,"departure":1522706654000,"zoneId":"NA","stopIndex":19,"stopSequence":20,"vertexType":"TRANSIT"},"to":{"name":"Destination","lon":-71.052185,"lat":48.426574,"arrival":1522706782000,"orig":"","vertexType":"NORMAL"},"legGeometry":{"points":"obqfH`ntpLHuBuEi@","length":3},"rentedBike":false,"transitLeg":false,"duration":128.0,"steps":[{"distance":43.835,"relativeDirection":"DEPART","streetName":"Rue Jacques-Cartier Est","absoluteDirection":"EAST","stayOn":false,"area":false,"bogusName":false,"lon":-71.05264627987177,"lat":48.42552496441786,"elevation":[]},{"distance":119.823,"relativeDirection":"LEFT","streetName":"Rue du Séminaire","absoluteDirection":"NORTH","stayOn":false,"area":false,"bogusName":false,"lon":-71.05205670000001,"lat":48.4254766,"elevation":[]}]}],"tooSloped":false}]},"debugOutput":{"precalculationTime":41,"pathCalculationTime":19,"pathTimes":[3,13,3],"renderingTime":0,"totalTime":60,"timedOut":false},"elevationMetadata":{"ellipsoidToGeoidDifference":-28.885904201182168,"geoidElevation":false}}