{"requestParameters":{"date":"2018/04/02","walkSpeed":"1.33","walkReluctance":"2.0","fromPlace":"48.416267,-71.073171","maxWalkDistance":"3000","waitReluctance":"1.0","carSpeed":"33","numItineraries":"3","waitAtBeginningFactor":"0.4","mode":"TRANSIT,WALK","ignoreRealtimeUpdates":"false","stairsReluctance":"2.0","toPlace":"48.423148,-71.052406","time":"15:0:00"},"plan":{"date":1522695600000,"from":{"name":"Origin","lon":-71.073171,"lat":48.416267,"orig":"","vertexType":"NORMAL"},"to":{"name":"Destination","lon":-71.052406,"lat":48.423148,"orig":"","vertexType":"NORMAL"},"itineraries":[{"duration":982,"startTime":1522696734000,"endTime":1522697716000,"walkTime":633,"transitTime":347,"waitingTime":2,"walkDistance":815.9693082666978,"walkLimitExceeded":false,"elevationLost":0.0,"elevationGained":0.0,"transfers":0,"legs":[{"startTime":1522696734000,"endTime":1522697186000,"departureDelay":0,"arrivalDelay":0,"realTime":false,"distance":585.958,"pathway":false,"mode":"WALK","route":"","agencyTimeZoneOffset":-14400000,"interlineWithPreviousLeg":false,"from":{"name":"Origin","lon":-71.073171,"lat":48.416267,"departure":1522696734000,"orig":"","vertexType":"NORMAL"},"to":{"name":"École secondaire de l'Odyssé Dominique-Racine","stopId":"1:580","stopCode":"580","lon":-71.067703,"lat":48.412977,"arrival":1522697186000,"departure":1522697187000,"zoneId":"NA","stopIndex":24,"stopSequence":25,"vertexType":"TRANSIT"},"legGeometry":{"points":"ghofHnmxpLXZ`CaH~CsIz@aCb@kAh@yA|AiEHQTHz@t@","length":11},"rentedBike":false,"transitLeg":false,"duration":452.0,"steps":[{"distance":17.882,"relativeDirection":"DEPART","streetName":"Rue McLaren","absoluteDirection":"SOUTHWEST","stayOn":false,"area":false,"bogusName":false,"lon":-71.07303683900132,"lat":48.41620721606169,"elevation":[]},{"distance":515.854,"relativeDirection":"LEFT","streetName":"Rue Des Oblats Est","absoluteDirection":"SOUTHEAST","stayOn":false,"area":false,"bogusName":false,"lon":-71.0731719,"lat":48.416073700000005,"elevation":[]},{"distance":52.222,"relativeDirection":"RIGHT","streetName":"Rue Bégin","absoluteDirection":"SOUTH","stayOn":false,"area":false,"bogusName":false,"lon":-71.06744280000001,"lat":48.413416500000004,"elevation":[]}]},{"startTime":1522697187000,"endTime":1522697534000,"departureDelay":0,"arrivalDelay":0,"realTime":false,"distance":1843.8727961518966,"pathway":false,"mode":"BUS","route":"15","agencyName":"Société de Transport du Saguenay","agencyUrl":"http://ville.saguenay.ca/fr/services-aux-citoyens/transport-sts","agencyTimeZoneOffset":-14400000,"routeColor":"FF00FF","routeType":3,"routeId":"1:15","routeTextColor":"FFFFFF","interlineWithPreviousLeg":false,"tripBlockId":"30","headsign":"Terminus Chicoutimi","agencyId":"0","tripId":"1:218104","serviceDate":"20180402","from":{"name":"École secondaire de l'Odyssé Dominique-Racine","stopId":"1:580","stopCode":"580","lon":-71.067703,"lat":48.412977,"arrival":1522697186000,"departure":1522697187000,"zoneId":"NA","stopIndex":24,"stopSequence":25,"vertexType":"TRANSIT"},"to":{"name":"Cégep de Chicoutimi (voie réservée)","stopId":"1:65","stopCode":"65","lon":-71.054799,"lat":48.423007,"arrival":1522697534000,"departure":1522697535000,"zoneId":"NA","stopIndex":31,"stopSequence":32,"vertexType":"TRANSIT"},"legGeometry":{"points":"ktnfH~lwpLsAkAoBwB_EcE{A_BoAmAk@o@cCaCkIkIaJaJUUwBaCj@wCjAsCzGoG_CoHL{D_@kAqD{CQr@iAcAy@w@L{@wAuA_B_B_EpLDh@NbB","length":28},"routeShortName":"15","routeLongName":"Term. Chic / Costco","rentedBike":false,"transitLeg":true,"duration":347.0,"steps":[]},{"startTime":1522697535000,"endTime":1522697716000,"departureDelay":0,"arrivalDelay":0,"realTime":false,"distance":229.88799999999998,"pathway":false,"mode":"WALK","route":"","agencyTimeZoneOffset":-14400000,"interlineWithPreviousLeg":false,"from":{"name":"Cégep de Chicoutimi (voie réservée)","stopId":"1:65","stopCode":"65","lon":-71.054799,"lat":48.423007,"arrival":1522697534000,"departure":1522697535000,"zoneId":"NA","stopIndex":31,"stopSequence":32,"vertexType":"TRANSIT"},"to":{"name":"Destination","lon":-71.052406,"lat":48.423148,"arrival":1522697716000,"orig":"","vertexType":"NORMAL"},"legGeometry":{"points":"srpfHl{tpLCSIo@A{@Tu@^iA_B_@VsBBW?o@","length":10},"rentedBike":false,"transitLeg":false,"duration":181.0,"steps":[{"distance":104.179,"relativeDirection":"DEPART","streetName":"bike path","absoluteDirection":"EAST","stayOn":false,"area":false,"bogusName":true,"lon":-71.0547862499772,"lat":48.42298365091458,"elevation":[]},{"distance":54.189,"relativeDirection":"LEFT","streetName":"path","absoluteDirection":"NORTH","stayOn":true,"area":false,"bogusName":true,"lon":-71.053503,"lat":48.4227993,"elevation":[]},{"distance":71.52,"relativeDirection":"RIGHT","streetName":"service road","absoluteDirection":"EAST","stayOn":false,"area":false,"bogusName":false,"lon":-71.05334280000001,"lat":48.4232749,"elevation":[]}]}],"tooSloped":false},{"duration":901,"startTime":1522696825000,"endTime":1522697726000,"walkTime":360,"transitTime":539,"waitingTime":2,"walkDistance":453.8534436049103,"walkLimitExceeded":false,"elevationLost":0.0,"elevationGained":0.0,"transfers":0,"legs":[{"startTime":1522696825000,"endTime":1522697004000,"departureDelay":0,"arrivalDelay":0,"realTime":false,"distance":223.83800000000002,"pathway":false,"mode":"WALK","route":"","agencyTimeZoneOffset":-14400000,"interlineWithPreviousLeg":false,"from":{"name":"Origin","lon":-71.073171,"lat":48.416267,"departure":1522696825000,"orig":"","vertexType":"NORMAL"},"to":{"name":"Boily / Oblats","stopId":"1:549","stopCode":"549","lon":-71.075339,"lat":48.416894,"arrival":1522697004000,"departure":1522697005000,"zoneId":"NA","stopIndex":24,"stopSequence":25,"vertexType":"TRANSIT"},"legGeometry":{"points":"ghofHnmxpLXZQ`@iCnHe@pAXV","length":6},"rentedBike":false,"transitLeg":false,"duration":179.0,"steps":[{"distance":17.882,"relativeDirection":"DEPART","streetName":"Rue McLaren","absoluteDirection":"SOUTHWEST","stayOn":false,"area":false,"bogusName":false,"lon":-71.07303683900132,"lat":48.41620721606169,"elevation":[]},{"distance":189.16500000000002,"relativeDirection":"RIGHT","streetName":"Rue Des Oblats Est","absoluteDirection":"NORTHWEST","stayOn":false,"area":false,"bogusName":false,"lon":-71.0731719,"lat":48.416073700000005,"elevation":[]},{"distance":16.791,"relativeDirection":"LEFT","streetName":"Rue Boily","absoluteDirection":"SOUTHWEST","stayOn":false,"area":false,"bogusName":false,"lon":-71.07527490000001,"lat":48.4170462,"elevation":[]}]},{"startTime":1522697005000,"endTime":1522697544000,"departureDelay":0,"arrivalDelay":0,"realTime":false,"distance":2347.017074606408,"pathway":false,"mode":"BUS","route":"14","agencyName":"Société de Transport du Saguenay","agencyUrl":"http://ville.saguenay.ca/fr/services-aux-citoyens/transport-sts","agencyTimeZoneOffset":-14400000,"routeColor":"C0C000","routeType":3,"routeId":"1:14","routeTextColor":"000000","interlineWithPreviousLeg":false,"tripBlockId":"31","headsign":"Terminus Chicoutimi","agencyId":"0","tripId":"1:218139","serviceDate":"20180402","from":{"name":"Boily / Oblats","stopId":"1:549","stopCode":"549","lon":-71.075339,"lat":48.416894,"arrival":1522697004000,"departure":1522697005000,"zoneId":"NA","stopIndex":24,"stopSequence":25,"vertexType":"TRANSIT"},"to":{"name":"Cégep de Chicoutimi (voie réservée)","stopId":"1:65","stopCode":"65","lon":-71.054799,"lat":48.423007,"arrival":1522697544000,"departure":1522697545000,"zoneId":"NA","stopIndex":31,"stopSequence":32,"vertexType":"TRANSIT"},"legGeometry":{"points":"wlofHh|xpL][aBhE}@}@oBmBwE{EwE{Ej@mBZeAa@SyEQg@CPcALuCx@{b@t@{[XoDd@sBl@iB~@gA`G{F{A{D_@sBFqDOq@iG{FGIoCkCgBgBsDpLHzBBT","length":32},"routeShortName":"14","routeLongName":"Coopérative","rentedBike":false,"transitLeg":true,"duration":539.0,"steps":[]},{"startTime":1522697545000,"endTime":1522697726000,"departureDelay":0,"arrivalDelay":0,"realTime":false,"distance":229.88799999999998,"pathway":false,"mode":"WALK","route":"","agencyTimeZoneOffset":-14400000,"interlineWithPreviousLeg":false,"from":{"name":"Cégep de Chicoutimi (voie réservée)","stopId":"1:65","stopCode":"65","lon":-71.054799,"lat":48.423007,"arrival":1522697544000,"departure":1522697545000,"zoneId":"NA","stopIndex":31,"stopSequence":32,"vertexType":"TRANSIT"},"to":{"name":"Destination","lon":-71.052406,"lat":48.423148,"arrival":1522697726000,"orig":"","vertexType":"NORMAL"},"legGeometry":{"points":"srpfHl{tpLCSIo@A{@Tu@^iA_B_@VsBBW?o@","length":10},"rentedBike":false,"transitLeg":false,"duration":181.0,"steps":[{"distance":104.179,"relativeDirection":"DEPART","streetName":"bike path","absoluteDirection":"EAST","stayOn":false,"area":false,"bogusName":true,"lon":-71.0547862499772,"lat":48.42298365091458,"elevation":[]},{"distance":54.189,"relativeDirection":"LEFT","streetName":"path","absoluteDirection":"NORTH","stayOn":true,"area":false,"bogusName":true,"lon":-71.053503,"lat":48.4227993,"elevation":[]},{"distance":71.52,"relativeDirection":"RIGHT","streetName":"service road","absoluteDirection":"EAST","stayOn":false,"area":false,"bogusName":false,"lon":-71.05334280000001,"lat":48.4232749,"elevation":[]}]}],"tooSloped":false},{"duration":901,"startTime":1522698625000,"endTime":1522699526000,"walkTime":360,"transitTime":539,"waitingTime":2,"walkDistance":453.8534436049103,"walkLimitExceeded":false,"elevationLost":0.0,"elevationGained":0.0,"transfers":0,"legs":[{"startTime":1522698625000,"endTime":1522698804000,"departureDelay":0,"arrivalDelay":0,"realTime":false,"distance":223.83800000000002,"pathway":false,"mode":"WALK","route":"","agencyTimeZoneOffset":-14400000,"interlineWithPreviousLeg":false,"from":{"name":"Origin","lon":-71.073171,"lat":48.416267,"departure":1522698625000,"orig":"","vertexType":"NORMAL"},"to":{"name":"Boily / Oblats","stopId":"1:549","stopCode":"549","lon":-71.075339,"lat":48.416894,"arrival":1522698804000,"departure":1522698805000,"zoneId":"NA","stopIndex":24,"stopSequence":25,"vertexType":"TRANSIT"},"legGeometry":{"points":"ghofHnmxpLXZQ`@iCnHe@pAXV","length":6},"rentedBike":false,"transitLeg":false,"duration":179.0,"steps":[{"distance":17.882,"relativeDirection":"DEPART","streetName":"Rue McLaren","absoluteDirection":"SOUTHWEST","stayOn":false,"area":false,"bogusName":false,"lon":-71.07303683900132,"lat":48.41620721606169,"elevation":[]},{"distance":189.16500000000002,"relativeDirection":"RIGHT","streetName":"Rue Des Oblats Est","absoluteDirection":"NORTHWEST","stayOn":false,"area":false,"bogusName":false,"lon":-71.0731719,"lat":48.416073700000005,"elevation":[]},{"distance":16.791,"relativeDirection":"LEFT","streetName":"Rue Boily","absoluteDirection":"SOUTHWEST","stayOn":false,"area":false,"bogusName":false,"lon":-71.07527490000001,"lat":48.4170462,"elevation":[]}]},{"startTime":1522698805000,"endTime":1522699344000,"departureDelay":0,"arrivalDelay":0,"realTime":false,"distance":2347.017074606408,"pathway":false,"mode":"BUS","route":"14","agencyName":"Société de Transport du Saguenay","agencyUrl":"http://ville.saguenay.ca/fr/services-aux-citoyens/transport-sts","agencyTimeZoneOffset":-14400000,"routeColor":"C0C000","routeType":3,"routeId":"1:14","routeTextColor":"000000","interlineWithPreviousLeg":false,"tripBlockId":"33","headsign":"Terminus Chicoutimi","agencyId":"0","tripId":"1:218190","serviceDate":"20180402","from":{"name":"Boily / Oblats","stopId":"1:549","stopCode":"549","lon":-71.075339,"lat":48.416894,"arrival":1522698804000,"departure":1522698805000,"zoneId":"NA","stopIndex":24,"stopSequence":25,"vertexType":"TRANSIT"},"to":{"name":"Cégep de Chicoutimi (voie réservée)","stopId":"1:65","stopCode":"65","lon":-71.054799,"lat":48.423007,"arrival":1522699344000,"departure":1522699345000,"zoneId":"NA","stopIndex":31,"stopSequence":32,"vertexType":"TRANSIT"},"legGeometry":{"points":"wlofHh|xpL][aBhE}@}@oBmBwE{EwE{Ej@mBZeAa@SyEQg@CPcALuCx@{b@t@{[XoDd@sBl@iB~@gA`G{F{A{D_@sBFqDOq@iG{FGIoCkCgBgBsDpLHzBBT","length":32},"routeShortName":"14","routeLongName":"Coopérative","rentedBike":false,"transitLeg":true,"duration":539.0,"steps":[]},{"startTime":1522699345000,"endTime":1522699526000,"departureDelay":0,"arrivalDelay":0,"realTime":false,"distance":229.88799999999998,"pathway":false,"mode":"WALK","route":"","agencyTimeZoneOffset":-14400000,"interlineWithPreviousLeg":false,"from":{"name":"Cégep de Chicoutimi (voie réservée)","stopId":"1:65","stopCode":"65","lon":-71.054799,"lat":48.423007,"arrival":1522699344000,"departure":1522699345000,"zoneId":"NA","stopIndex":31,"stopSequence":32,"vertexType":"TRANSIT"},"to":{"name":"Destination","lon":-71.052406,"lat":48.423148,"arrival":1522699526000,"orig":"","vertexType":"NORMAL"},"legGeometry":{"points":"srpfHl{tpLCSIo@A{@Tu@^iA_B_@VsBBW?o@","length":10},"rentedBike":false,"transitLeg":false,"duration":181.0,"steps":[{"distance":104.179,"relativeDirection":"DEPART","streetName":"bike path","absoluteDirection":"EAST","stayOn":false,"area":false,"bogusName":true,"lon":-71.0547862499772,"lat":48.42298365091458,"elevation":[]},{"distance":54.189,"relativeDirection":"LEFT","streetName":"path","absoluteDirection":"NORTH","stayOn":true,"area":false,"bogusName":true,"lon":-71.053503,"lat":48.4227993,"elevation":[]},{"distance":71.52,"relativeDirection":"RIGHT","streetName":"service road","absoluteDirection":"EAST","stayOn":false,"area":false,"bogusName":false,"lon":-71.05334280000001,"lat":48.4232749,"elevation":[]}]}],"tooSloped":false}]},"debugOutput":{"precalculationTime":30,"pathCalculationTime":21,"pathTimes":[13,3,5],"renderingTime":0,"totalTime":51,"timedOut":false},"elevationMetadata":{"ellipsoidToGeoidDifference":-28.885904201182168,"geoidElevation":false}}